{
  "symbol": "7711",
  "name": "永擎",
  "tradeDate": "2026-07-22",
  "market": "TWSE",
  "instrumentType": "stock",
  "quote": {
    "open": 307,
    "high": 311,
    "low": 304.5,
    "close": 308.5,
    "change": 4.5,
    "changePercent": 1.48,
    "tradeVolume": 170863,
    "transactionCount": 295,
    "tradeValue": 52727499,
    "peRatio": 27.54
  },
  "dailyRangePercent": 2.13,
  "turnoverAverageValue": 178737.28,
  "pricePosition": 61.5,
  "liquidityScore": 45,
  "priceStrengthScore": 61.4,
  "valuationRiskScore": 55,
  "snapshotScore": 52.4,
  "status": "中性",
  "risks": [],
  "tags": [
    "中性",
    "上漲"
  ],
  "sources": [
    {
      "type": "official",
      "name": "TWSE",
      "field": "quote"
    },
    {
      "type": "derived",
      "name": "GULI deterministic rules",
      "field": "scores"
    }
  ],
  "warnings": []
}
