{
  "symbol": "2492",
  "name": "華新科",
  "tradeDate": "2026-07-15",
  "market": "TWSE",
  "instrumentType": "stock",
  "quote": {
    "open": 395,
    "high": 395,
    "low": 370.5,
    "close": 379,
    "change": -11,
    "changePercent": -2.82,
    "tradeVolume": 23095183,
    "transactionCount": 25539,
    "tradeValue": 8795388513,
    "peRatio": 72.61
  },
  "dailyRangePercent": 6.61,
  "turnoverAverageValue": 344390.48,
  "pricePosition": 34.7,
  "liquidityScore": 96.9,
  "priceStrengthScore": 34.3,
  "valuationRiskScore": 90,
  "snapshotScore": 51.4,
  "status": "中性",
  "risks": [
    {
      "code": "unusually_high_pe",
      "severity": "medium",
      "title": "本益比偏高",
      "reason": "官方本益比 72.61 達一般性 60 倍門檻；未做產業比較。",
      "source": "official"
    }
  ],
  "tags": [
    "中性",
    "下跌"
  ],
  "sources": [
    {
      "type": "official",
      "name": "TWSE",
      "field": "quote"
    },
    {
      "type": "derived",
      "name": "GULI deterministic rules",
      "field": "scores"
    }
  ],
  "warnings": []
}
