{
  "schemaVersion": "1.0",
  "symbol": "1231",
  "name": "聯華食",
  "market": "TWSE",
  "source": "TWSE",
  "sourceUrl": "https://www.twse.com.tw/rwd/zh/afterTrading/STOCK_DAY",
  "fetchedAt": "2026-07-17T03:13:24.152Z",
  "firstTradeDate": "2025-07-01",
  "lastTradeDate": "2026-07-16",
  "recordCount": 254,
  "status": "official",
  "warnings": [],
  "prices": [
    {
      "tradeDate": "2025-07-01",
      "open": 139.5,
      "high": 144.5,
      "low": 139.5,
      "close": 143.5,
      "change": 3,
      "volume": 370707,
      "tradingAmount": 53158735,
      "transactionCount": 1041
    },
    {
      "tradeDate": "2025-07-02",
      "open": 144.5,
      "high": 144.5,
      "low": 142.5,
      "close": 144,
      "change": 0.5,
      "volume": 248646,
      "tradingAmount": 35630536,
      "transactionCount": 1558
    },
    {
      "tradeDate": "2025-07-03",
      "open": 144,
      "high": 146,
      "low": 142,
      "close": 142,
      "change": -2,
      "volume": 368454,
      "tradingAmount": 52986095,
      "transactionCount": 789
    },
    {
      "tradeDate": "2025-07-04",
      "open": 142,
      "high": 143,
      "low": 140,
      "close": 141.5,
      "change": -0.5,
      "volume": 180591,
      "tradingAmount": 25503926,
      "transactionCount": 525
    },
    {
      "tradeDate": "2025-07-07",
      "open": 142.5,
      "high": 142.5,
      "low": 140.5,
      "close": 141,
      "change": -0.5,
      "volume": 85864,
      "tradingAmount": 12135073,
      "transactionCount": 342
    },
    {
      "tradeDate": "2025-07-08",
      "open": 141.5,
      "high": 141.5,
      "low": 138.5,
      "close": 139,
      "change": -2,
      "volume": 208071,
      "tradingAmount": 29008060,
      "transactionCount": 529
    },
    {
      "tradeDate": "2025-07-09",
      "open": 139,
      "high": 140,
      "low": 138,
      "close": 139,
      "change": 0,
      "volume": 153172,
      "tradingAmount": 21362492,
      "transactionCount": 324
    },
    {
      "tradeDate": "2025-07-10",
      "open": 139,
      "high": 141.5,
      "low": 139,
      "close": 141,
      "change": 2,
      "volume": 142071,
      "tradingAmount": 19974921,
      "transactionCount": 326
    },
    {
      "tradeDate": "2025-07-11",
      "open": 141.5,
      "high": 144.5,
      "low": 141.5,
      "close": 142,
      "change": 1,
      "volume": 280184,
      "tradingAmount": 40037413,
      "transactionCount": 525
    },
    {
      "tradeDate": "2025-07-14",
      "open": 142.5,
      "high": 147,
      "low": 141.5,
      "close": 143,
      "change": 1,
      "volume": 310183,
      "tradingAmount": 44636835,
      "transactionCount": 553
    },
    {
      "tradeDate": "2025-07-15",
      "open": 144.5,
      "high": 144.5,
      "low": 142.5,
      "close": 143.5,
      "change": 0.5,
      "volume": 237607,
      "tradingAmount": 34093152,
      "transactionCount": 458
    },
    {
      "tradeDate": "2025-07-16",
      "open": 143.5,
      "high": 145,
      "low": 143,
      "close": 143,
      "change": -0.5,
      "volume": 183789,
      "tradingAmount": 26403667,
      "transactionCount": 391
    },
    {
      "tradeDate": "2025-07-17",
      "open": 142.5,
      "high": 143,
      "low": 142,
      "close": 142,
      "change": -1,
      "volume": 159868,
      "tradingAmount": 22767698,
      "transactionCount": 368
    },
    {
      "tradeDate": "2025-07-18",
      "open": 142,
      "high": 144,
      "low": 142,
      "close": 144,
      "change": 2,
      "volume": 108626,
      "tradingAmount": 15520192,
      "transactionCount": 319
    },
    {
      "tradeDate": "2025-07-21",
      "open": 144,
      "high": 144,
      "low": 141,
      "close": 141.5,
      "change": -2.5,
      "volume": 168794,
      "tradingAmount": 24014164,
      "transactionCount": 505
    },
    {
      "tradeDate": "2025-07-22",
      "open": 141.5,
      "high": 141.5,
      "low": 138.5,
      "close": 138.5,
      "change": -3,
      "volume": 319493,
      "tradingAmount": 44638824,
      "transactionCount": 843
    },
    {
      "tradeDate": "2025-07-23",
      "open": 139,
      "high": 140.5,
      "low": 139,
      "close": 140,
      "change": 1.5,
      "volume": 99932,
      "tradingAmount": 13987165,
      "transactionCount": 271
    },
    {
      "tradeDate": "2025-07-24",
      "open": 140,
      "high": 141.5,
      "low": 138.5,
      "close": 140.5,
      "change": 0.5,
      "volume": 126058,
      "tradingAmount": 17671978,
      "transactionCount": 317
    },
    {
      "tradeDate": "2025-07-25",
      "open": 139.5,
      "high": 141,
      "low": 139.5,
      "close": 140,
      "change": -0.5,
      "volume": 48461,
      "tradingAmount": 6805754,
      "transactionCount": 206
    },
    {
      "tradeDate": "2025-07-28",
      "open": 139,
      "high": 142,
      "low": 139,
      "close": 140.5,
      "change": 0.5,
      "volume": 66146,
      "tradingAmount": 9330302,
      "transactionCount": 242
    },
    {
      "tradeDate": "2025-07-29",
      "open": 140,
      "high": 141,
      "low": 138,
      "close": 138.5,
      "change": -2,
      "volume": 361634,
      "tradingAmount": 50205594,
      "transactionCount": 897
    },
    {
      "tradeDate": "2025-07-30",
      "open": 138.5,
      "high": 140,
      "low": 137.5,
      "close": 138.5,
      "change": 0,
      "volume": 282617,
      "tradingAmount": 39135691,
      "transactionCount": 549
    },
    {
      "tradeDate": "2025-07-31",
      "open": 138.5,
      "high": 139,
      "low": 137.5,
      "close": 138,
      "change": -0.5,
      "volume": 193346,
      "tradingAmount": 26737113,
      "transactionCount": 462
    },
    {
      "tradeDate": "2025-08-01",
      "open": 137,
      "high": 140.5,
      "low": 137,
      "close": 139.5,
      "change": 1.5,
      "volume": 160107,
      "tradingAmount": 22266442,
      "transactionCount": 398
    },
    {
      "tradeDate": "2025-08-04",
      "open": 139,
      "high": 142.5,
      "low": 139,
      "close": 142,
      "change": 2.5,
      "volume": 228519,
      "tradingAmount": 32277349,
      "transactionCount": 429
    },
    {
      "tradeDate": "2025-08-05",
      "open": 141.5,
      "high": 145.5,
      "low": 141.5,
      "close": 144,
      "change": 2,
      "volume": 416677,
      "tradingAmount": 59888051,
      "transactionCount": 644
    },
    {
      "tradeDate": "2025-08-06",
      "open": 146,
      "high": 153,
      "low": 145.5,
      "close": 149.5,
      "change": 5.5,
      "volume": 747158,
      "tradingAmount": 111008475,
      "transactionCount": 3222
    },
    {
      "tradeDate": "2025-08-07",
      "open": 152,
      "high": 154.5,
      "low": 150.5,
      "close": 154,
      "change": 4.5,
      "volume": 649196,
      "tradingAmount": 99204609,
      "transactionCount": 1524
    },
    {
      "tradeDate": "2025-08-08",
      "open": 153,
      "high": 153.5,
      "low": 148,
      "close": 148.5,
      "change": -5.5,
      "volume": 671194,
      "tradingAmount": 100616134,
      "transactionCount": 7055
    },
    {
      "tradeDate": "2025-08-11",
      "open": 148.5,
      "high": 148.5,
      "low": 143.5,
      "close": 143.5,
      "change": -5,
      "volume": 449382,
      "tradingAmount": 65014431,
      "transactionCount": 1287
    },
    {
      "tradeDate": "2025-08-12",
      "open": 144.5,
      "high": 144.5,
      "low": 142.5,
      "close": 142.5,
      "change": -1,
      "volume": 358163,
      "tradingAmount": 51368224,
      "transactionCount": 748
    },
    {
      "tradeDate": "2025-08-13",
      "open": 143.5,
      "high": 144,
      "low": 142,
      "close": 143,
      "change": 0.5,
      "volume": 336381,
      "tradingAmount": 48079795,
      "transactionCount": 702
    },
    {
      "tradeDate": "2025-08-14",
      "open": 143.5,
      "high": 148.5,
      "low": 143.5,
      "close": 147.5,
      "change": 4.5,
      "volume": 305207,
      "tradingAmount": 44647469,
      "transactionCount": 1016
    },
    {
      "tradeDate": "2025-08-15",
      "open": 148.5,
      "high": 149,
      "low": 146,
      "close": 149,
      "change": 1.5,
      "volume": 275160,
      "tradingAmount": 40611106,
      "transactionCount": 1189
    },
    {
      "tradeDate": "2025-08-18",
      "open": 149,
      "high": 152,
      "low": 147.5,
      "close": 151.5,
      "change": 2.5,
      "volume": 588676,
      "tradingAmount": 88586802,
      "transactionCount": 936
    },
    {
      "tradeDate": "2025-08-19",
      "open": 152.5,
      "high": 153,
      "low": 149.5,
      "close": 150.5,
      "change": -1,
      "volume": 534663,
      "tradingAmount": 80856934,
      "transactionCount": 2128
    },
    {
      "tradeDate": "2025-08-20",
      "open": 150.5,
      "high": 152,
      "low": 149,
      "close": 149.5,
      "change": -1,
      "volume": 992513,
      "tradingAmount": 149254100,
      "transactionCount": 1525
    },
    {
      "tradeDate": "2025-08-21",
      "open": 136.5,
      "high": 141,
      "low": 136.5,
      "close": 139,
      "change": 0,
      "volume": 1180796,
      "tradingAmount": 164048232,
      "transactionCount": 3769
    },
    {
      "tradeDate": "2025-08-22",
      "open": 139,
      "high": 139,
      "low": 137.5,
      "close": 138.5,
      "change": -0.5,
      "volume": 378803,
      "tradingAmount": 52443378,
      "transactionCount": 836
    },
    {
      "tradeDate": "2025-08-25",
      "open": 138.5,
      "high": 139,
      "low": 137,
      "close": 138.5,
      "change": 0,
      "volume": 319517,
      "tradingAmount": 44193815,
      "transactionCount": 725
    },
    {
      "tradeDate": "2025-08-26",
      "open": 138.5,
      "high": 138.5,
      "low": 137,
      "close": 137.5,
      "change": -1,
      "volume": 269646,
      "tradingAmount": 37183365,
      "transactionCount": 730
    },
    {
      "tradeDate": "2025-08-27",
      "open": 137.5,
      "high": 138,
      "low": 135,
      "close": 135,
      "change": -2.5,
      "volume": 483849,
      "tradingAmount": 65944252,
      "transactionCount": 1427
    },
    {
      "tradeDate": "2025-08-28",
      "open": 135,
      "high": 137.5,
      "low": 133.5,
      "close": 137,
      "change": 2,
      "volume": 272567,
      "tradingAmount": 37106678,
      "transactionCount": 627
    },
    {
      "tradeDate": "2025-08-29",
      "open": 137.5,
      "high": 138,
      "low": 136.5,
      "close": 136.5,
      "change": -0.5,
      "volume": 146748,
      "tradingAmount": 20160442,
      "transactionCount": 376
    },
    {
      "tradeDate": "2025-09-01",
      "open": 137.5,
      "high": 137.5,
      "low": 134.5,
      "close": 134.5,
      "change": -2,
      "volume": 243627,
      "tradingAmount": 33016093,
      "transactionCount": 706
    },
    {
      "tradeDate": "2025-09-02",
      "open": 134.5,
      "high": 139.5,
      "low": 134.5,
      "close": 138.5,
      "change": 4,
      "volume": 381755,
      "tradingAmount": 52698949,
      "transactionCount": 535
    },
    {
      "tradeDate": "2025-09-03",
      "open": 138.5,
      "high": 138.5,
      "low": 136,
      "close": 136.5,
      "change": -2,
      "volume": 197059,
      "tradingAmount": 26972853,
      "transactionCount": 1141
    },
    {
      "tradeDate": "2025-09-04",
      "open": 136.5,
      "high": 138.5,
      "low": 136.5,
      "close": 138,
      "change": 1.5,
      "volume": 119802,
      "tradingAmount": 16509472,
      "transactionCount": 291
    },
    {
      "tradeDate": "2025-09-05",
      "open": 137,
      "high": 137,
      "low": 135.5,
      "close": 136,
      "change": -2,
      "volume": 248533,
      "tradingAmount": 33848413,
      "transactionCount": 624
    },
    {
      "tradeDate": "2025-09-08",
      "open": 136,
      "high": 136,
      "low": 135,
      "close": 135,
      "change": -1,
      "volume": 204062,
      "tradingAmount": 27635847,
      "transactionCount": 600
    },
    {
      "tradeDate": "2025-09-09",
      "open": 135,
      "high": 136,
      "low": 134.5,
      "close": 135,
      "change": 0,
      "volume": 160338,
      "tradingAmount": 21676146,
      "transactionCount": 411
    },
    {
      "tradeDate": "2025-09-10",
      "open": 135.5,
      "high": 135.5,
      "low": 133,
      "close": 133.5,
      "change": -1.5,
      "volume": 421939,
      "tradingAmount": 56551446,
      "transactionCount": 1188
    },
    {
      "tradeDate": "2025-09-11",
      "open": 133,
      "high": 134,
      "low": 132.5,
      "close": 133,
      "change": -0.5,
      "volume": 300811,
      "tradingAmount": 40074284,
      "transactionCount": 800
    },
    {
      "tradeDate": "2025-09-12",
      "open": 133.5,
      "high": 134.5,
      "low": 133,
      "close": 134,
      "change": 1,
      "volume": 132903,
      "tradingAmount": 17780333,
      "transactionCount": 374
    },
    {
      "tradeDate": "2025-09-15",
      "open": 134,
      "high": 134.5,
      "low": 133,
      "close": 133,
      "change": -1,
      "volume": 161559,
      "tradingAmount": 21569345,
      "transactionCount": 564
    },
    {
      "tradeDate": "2025-09-16",
      "open": 134.5,
      "high": 134.5,
      "low": 133,
      "close": 133.5,
      "change": 0.5,
      "volume": 151849,
      "tradingAmount": 20270703,
      "transactionCount": 383
    },
    {
      "tradeDate": "2025-09-17",
      "open": 134.5,
      "high": 134.5,
      "low": 133,
      "close": 133,
      "change": -0.5,
      "volume": 146989,
      "tradingAmount": 19625247,
      "transactionCount": 378
    },
    {
      "tradeDate": "2025-09-18",
      "open": 134,
      "high": 134,
      "low": 132,
      "close": 132,
      "change": -1,
      "volume": 206377,
      "tradingAmount": 27383971,
      "transactionCount": 734
    },
    {
      "tradeDate": "2025-09-19",
      "open": 132,
      "high": 132,
      "low": 130.5,
      "close": 131.5,
      "change": -0.5,
      "volume": 271929,
      "tradingAmount": 35740354,
      "transactionCount": 928
    },
    {
      "tradeDate": "2025-09-22",
      "open": 132.5,
      "high": 132.5,
      "low": 130,
      "close": 130.5,
      "change": -1,
      "volume": 331866,
      "tradingAmount": 43419939,
      "transactionCount": 1283
    },
    {
      "tradeDate": "2025-09-23",
      "open": 130,
      "high": 130.5,
      "low": 127.5,
      "close": 128.5,
      "change": -2,
      "volume": 639463,
      "tradingAmount": 82179698,
      "transactionCount": 2022
    },
    {
      "tradeDate": "2025-09-24",
      "open": 129,
      "high": 130,
      "low": 128.5,
      "close": 129,
      "change": 0.5,
      "volume": 241352,
      "tradingAmount": 31241945,
      "transactionCount": 717
    },
    {
      "tradeDate": "2025-09-25",
      "open": 131,
      "high": 131,
      "low": 129,
      "close": 130,
      "change": 1,
      "volume": 159292,
      "tradingAmount": 20695514,
      "transactionCount": 518
    },
    {
      "tradeDate": "2025-09-26",
      "open": 130,
      "high": 130,
      "low": 127,
      "close": 128.5,
      "change": -1.5,
      "volume": 463282,
      "tradingAmount": 59388901,
      "transactionCount": 1641
    },
    {
      "tradeDate": "2025-09-30",
      "open": 129.5,
      "high": 129.5,
      "low": 127,
      "close": 128.5,
      "change": 0,
      "volume": 231014,
      "tradingAmount": 29554607,
      "transactionCount": 1443
    },
    {
      "tradeDate": "2025-10-01",
      "open": 128.5,
      "high": 128.5,
      "low": 127,
      "close": 128,
      "change": -0.5,
      "volume": 159053,
      "tradingAmount": 20367083,
      "transactionCount": 712
    },
    {
      "tradeDate": "2025-10-02",
      "open": 127,
      "high": 127,
      "low": 124.5,
      "close": 125.5,
      "change": -2.5,
      "volume": 659227,
      "tradingAmount": 82791131,
      "transactionCount": 2939
    },
    {
      "tradeDate": "2025-10-03",
      "open": 125,
      "high": 125,
      "low": 119.5,
      "close": 121.5,
      "change": -4,
      "volume": 1278799,
      "tradingAmount": 155281996,
      "transactionCount": 3847
    },
    {
      "tradeDate": "2025-10-07",
      "open": 120.5,
      "high": 120.5,
      "low": 115.5,
      "close": 116.5,
      "change": -5,
      "volume": 1587372,
      "tradingAmount": 185772620,
      "transactionCount": 4550
    },
    {
      "tradeDate": "2025-10-08",
      "open": 114.5,
      "high": 118,
      "low": 114.5,
      "close": 117,
      "change": 0.5,
      "volume": 545260,
      "tradingAmount": 63397062,
      "transactionCount": 1219
    },
    {
      "tradeDate": "2025-10-09",
      "open": 117.5,
      "high": 118,
      "low": 116,
      "close": 118,
      "change": 1,
      "volume": 340733,
      "tradingAmount": 39907765,
      "transactionCount": 1103
    },
    {
      "tradeDate": "2025-10-13",
      "open": 116.5,
      "high": 116.5,
      "low": 115,
      "close": 115.5,
      "change": -2.5,
      "volume": 489558,
      "tradingAmount": 56744140,
      "transactionCount": 1401
    },
    {
      "tradeDate": "2025-10-14",
      "open": 115.5,
      "high": 116,
      "low": 114,
      "close": 114,
      "change": -1.5,
      "volume": 565051,
      "tradingAmount": 64945562,
      "transactionCount": 1797
    },
    {
      "tradeDate": "2025-10-15",
      "open": 115.5,
      "high": 115.5,
      "low": 113,
      "close": 113.5,
      "change": -0.5,
      "volume": 392566,
      "tradingAmount": 44698850,
      "transactionCount": 1192
    },
    {
      "tradeDate": "2025-10-16",
      "open": 113.5,
      "high": 114,
      "low": 112.5,
      "close": 113,
      "change": -0.5,
      "volume": 427873,
      "tradingAmount": 48438248,
      "transactionCount": 1081
    },
    {
      "tradeDate": "2025-10-17",
      "open": 113,
      "high": 116,
      "low": 113,
      "close": 116,
      "change": 3,
      "volume": 309236,
      "tradingAmount": 35471591,
      "transactionCount": 742
    },
    {
      "tradeDate": "2025-10-20",
      "open": 115.5,
      "high": 116,
      "low": 112,
      "close": 113,
      "change": -3,
      "volume": 512312,
      "tradingAmount": 57884404,
      "transactionCount": 1632
    },
    {
      "tradeDate": "2025-10-21",
      "open": 113,
      "high": 113,
      "low": 111,
      "close": 111,
      "change": -2,
      "volume": 543764,
      "tradingAmount": 60680378,
      "transactionCount": 1912
    },
    {
      "tradeDate": "2025-10-22",
      "open": 110,
      "high": 112.5,
      "low": 110,
      "close": 112,
      "change": 1,
      "volume": 386284,
      "tradingAmount": 43152042,
      "transactionCount": 803
    },
    {
      "tradeDate": "2025-10-23",
      "open": 112.5,
      "high": 112.5,
      "low": 111,
      "close": 112,
      "change": 0,
      "volume": 224079,
      "tradingAmount": 25064248,
      "transactionCount": 628
    },
    {
      "tradeDate": "2025-10-27",
      "open": 113.5,
      "high": 113.5,
      "low": 111.5,
      "close": 113,
      "change": 1,
      "volume": 280782,
      "tradingAmount": 31643209,
      "transactionCount": 709
    },
    {
      "tradeDate": "2025-10-28",
      "open": 114.5,
      "high": 114.5,
      "low": 112,
      "close": 113,
      "change": 0,
      "volume": 196080,
      "tradingAmount": 22165788,
      "transactionCount": 529
    },
    {
      "tradeDate": "2025-10-29",
      "open": 112.5,
      "high": 113.5,
      "low": 111.5,
      "close": 113,
      "change": 0,
      "volume": 288962,
      "tradingAmount": 32506027,
      "transactionCount": 648
    },
    {
      "tradeDate": "2025-10-30",
      "open": 112.5,
      "high": 112.5,
      "low": 110.5,
      "close": 111,
      "change": -2,
      "volume": 387787,
      "tradingAmount": 43109234,
      "transactionCount": 1545
    },
    {
      "tradeDate": "2025-10-31",
      "open": 111,
      "high": 112,
      "low": 111,
      "close": 111,
      "change": 0,
      "volume": 204554,
      "tradingAmount": 22738996,
      "transactionCount": 554
    },
    {
      "tradeDate": "2025-11-03",
      "open": 111,
      "high": 111,
      "low": 108,
      "close": 108.5,
      "change": -2.5,
      "volume": 625417,
      "tradingAmount": 68095767,
      "transactionCount": 1983
    },
    {
      "tradeDate": "2025-11-04",
      "open": 108.5,
      "high": 110,
      "low": 108,
      "close": 109,
      "change": 0.5,
      "volume": 253767,
      "tradingAmount": 27653221,
      "transactionCount": 583
    },
    {
      "tradeDate": "2025-11-05",
      "open": 109,
      "high": 109,
      "low": 107.5,
      "close": 109,
      "change": 0,
      "volume": 295751,
      "tradingAmount": 32042835,
      "transactionCount": 746
    },
    {
      "tradeDate": "2025-11-06",
      "open": 109.5,
      "high": 110,
      "low": 108.5,
      "close": 109.5,
      "change": 0.5,
      "volume": 149378,
      "tradingAmount": 16352862,
      "transactionCount": 438
    },
    {
      "tradeDate": "2025-11-07",
      "open": 109.5,
      "high": 109.5,
      "low": 108,
      "close": 108.5,
      "change": -1,
      "volume": 130533,
      "tradingAmount": 14183473,
      "transactionCount": 764
    },
    {
      "tradeDate": "2025-11-10",
      "open": 108,
      "high": 108,
      "low": 102.5,
      "close": 103.5,
      "change": -5,
      "volume": 928826,
      "tradingAmount": 96280405,
      "transactionCount": 2673
    },
    {
      "tradeDate": "2025-11-11",
      "open": 102,
      "high": 103,
      "low": 99.2,
      "close": 99.6,
      "change": -3.9,
      "volume": 1779078,
      "tradingAmount": 178189728,
      "transactionCount": 3481
    },
    {
      "tradeDate": "2025-11-12",
      "open": 99.6,
      "high": 100.5,
      "low": 98.5,
      "close": 98.6,
      "change": -1,
      "volume": 1226961,
      "tradingAmount": 121634061,
      "transactionCount": 3061
    },
    {
      "tradeDate": "2025-11-13",
      "open": 97.8,
      "high": 97.8,
      "low": 93,
      "close": 93.8,
      "change": -4.8,
      "volume": 2196455,
      "tradingAmount": 207263395,
      "transactionCount": 4490
    },
    {
      "tradeDate": "2025-11-14",
      "open": 93.8,
      "high": 94.9,
      "low": 92.3,
      "close": 94.9,
      "change": 1.1,
      "volume": 1112668,
      "tradingAmount": 104025916,
      "transactionCount": 3538
    },
    {
      "tradeDate": "2025-11-17",
      "open": 95.2,
      "high": 98.5,
      "low": 93.1,
      "close": 97.8,
      "change": 2.9,
      "volume": 859969,
      "tradingAmount": 83177153,
      "transactionCount": 3460
    },
    {
      "tradeDate": "2025-11-18",
      "open": 97,
      "high": 97.3,
      "low": 93.2,
      "close": 93.9,
      "change": -3.9,
      "volume": 742686,
      "tradingAmount": 70377128,
      "transactionCount": 2811
    },
    {
      "tradeDate": "2025-11-19",
      "open": 94,
      "high": 94.4,
      "low": 93,
      "close": 93.2,
      "change": -0.7,
      "volume": 302341,
      "tradingAmount": 28309016,
      "transactionCount": 788
    },
    {
      "tradeDate": "2025-11-20",
      "open": 93.7,
      "high": 95.7,
      "low": 93.7,
      "close": 95,
      "change": 1.8,
      "volume": 288970,
      "tradingAmount": 27520432,
      "transactionCount": 530
    },
    {
      "tradeDate": "2025-11-21",
      "open": 94.6,
      "high": 96.4,
      "low": 94.4,
      "close": 96.4,
      "change": 1.4,
      "volume": 313776,
      "tradingAmount": 30055449,
      "transactionCount": 653
    },
    {
      "tradeDate": "2025-11-24",
      "open": 96.2,
      "high": 98,
      "low": 96.2,
      "close": 97.1,
      "change": 0.7,
      "volume": 400567,
      "tradingAmount": 38925498,
      "transactionCount": 675
    },
    {
      "tradeDate": "2025-11-25",
      "open": 98.1,
      "high": 98.5,
      "low": 97.4,
      "close": 97.9,
      "change": 0.8,
      "volume": 288629,
      "tradingAmount": 28252495,
      "transactionCount": 564
    },
    {
      "tradeDate": "2025-11-26",
      "open": 98,
      "high": 101.5,
      "low": 98,
      "close": 101,
      "change": 3.1,
      "volume": 512705,
      "tradingAmount": 51517147,
      "transactionCount": 852
    },
    {
      "tradeDate": "2025-11-27",
      "open": 100.5,
      "high": 101,
      "low": 100,
      "close": 100,
      "change": -1,
      "volume": 183973,
      "tradingAmount": 18495703,
      "transactionCount": 455
    },
    {
      "tradeDate": "2025-11-28",
      "open": 100,
      "high": 101,
      "low": 99,
      "close": 100,
      "change": 0,
      "volume": 305550,
      "tradingAmount": 30503764,
      "transactionCount": 565
    },
    {
      "tradeDate": "2025-12-01",
      "open": 100,
      "high": 102,
      "low": 99.8,
      "close": 99.8,
      "change": -0.2,
      "volume": 241801,
      "tradingAmount": 24283491,
      "transactionCount": 499
    },
    {
      "tradeDate": "2025-12-02",
      "open": 99.8,
      "high": 100,
      "low": 99.2,
      "close": 99.7,
      "change": -0.1,
      "volume": 151874,
      "tradingAmount": 15127862,
      "transactionCount": 427
    },
    {
      "tradeDate": "2025-12-03",
      "open": 100,
      "high": 100.5,
      "low": 99.6,
      "close": 100,
      "change": 0.3,
      "volume": 157409,
      "tradingAmount": 15750443,
      "transactionCount": 340
    },
    {
      "tradeDate": "2025-12-04",
      "open": 100,
      "high": 100.5,
      "low": 98.7,
      "close": 99.2,
      "change": -0.8,
      "volume": 228785,
      "tradingAmount": 22716716,
      "transactionCount": 767
    },
    {
      "tradeDate": "2025-12-05",
      "open": 99.3,
      "high": 100,
      "low": 99.1,
      "close": 99.2,
      "change": 0,
      "volume": 150340,
      "tradingAmount": 14963036,
      "transactionCount": 343
    },
    {
      "tradeDate": "2025-12-08",
      "open": 99.5,
      "high": 99.5,
      "low": 98.5,
      "close": 98.6,
      "change": -0.6,
      "volume": 259865,
      "tradingAmount": 25675569,
      "transactionCount": 655
    },
    {
      "tradeDate": "2025-12-09",
      "open": 98.4,
      "high": 98.6,
      "low": 97.6,
      "close": 98.6,
      "change": 0,
      "volume": 259450,
      "tradingAmount": 25463558,
      "transactionCount": 665
    },
    {
      "tradeDate": "2025-12-10",
      "open": 98.6,
      "high": 99.5,
      "low": 97.6,
      "close": 97.8,
      "change": -0.8,
      "volume": 282545,
      "tradingAmount": 27770778,
      "transactionCount": 700
    },
    {
      "tradeDate": "2025-12-11",
      "open": 97.8,
      "high": 98.5,
      "low": 97.6,
      "close": 97.7,
      "change": -0.1,
      "volume": 218885,
      "tradingAmount": 21440694,
      "transactionCount": 501
    },
    {
      "tradeDate": "2025-12-12",
      "open": 98.2,
      "high": 99.7,
      "low": 98.2,
      "close": 98.5,
      "change": 0.8,
      "volume": 183443,
      "tradingAmount": 18194766,
      "transactionCount": 404
    },
    {
      "tradeDate": "2025-12-15",
      "open": 98.8,
      "high": 98.8,
      "low": 96.8,
      "close": 97,
      "change": -1.5,
      "volume": 369407,
      "tradingAmount": 36011474,
      "transactionCount": 1073
    },
    {
      "tradeDate": "2025-12-16",
      "open": 96.1,
      "high": 96.7,
      "low": 95.5,
      "close": 96.3,
      "change": -0.7,
      "volume": 301743,
      "tradingAmount": 28959519,
      "transactionCount": 918
    },
    {
      "tradeDate": "2025-12-17",
      "open": 96.8,
      "high": 97.7,
      "low": 96,
      "close": 96.8,
      "change": 0.5,
      "volume": 196801,
      "tradingAmount": 19095497,
      "transactionCount": 366
    },
    {
      "tradeDate": "2025-12-18",
      "open": 96.8,
      "high": 98.4,
      "low": 96.1,
      "close": 98.4,
      "change": 1.6,
      "volume": 190987,
      "tradingAmount": 18563975,
      "transactionCount": 839
    },
    {
      "tradeDate": "2025-12-19",
      "open": 97.8,
      "high": 99,
      "low": 97.3,
      "close": 98.4,
      "change": 0,
      "volume": 178554,
      "tradingAmount": 17574081,
      "transactionCount": 402
    },
    {
      "tradeDate": "2025-12-22",
      "open": 98.5,
      "high": 99.1,
      "low": 97.8,
      "close": 99,
      "change": 0.6,
      "volume": 256452,
      "tradingAmount": 25232214,
      "transactionCount": 502
    },
    {
      "tradeDate": "2025-12-23",
      "open": 99,
      "high": 99.7,
      "low": 97.8,
      "close": 97.8,
      "change": -1.2,
      "volume": 280059,
      "tradingAmount": 27586246,
      "transactionCount": 1780
    },
    {
      "tradeDate": "2025-12-24",
      "open": 97.9,
      "high": 98.7,
      "low": 97.3,
      "close": 97.9,
      "change": 0.1,
      "volume": 193234,
      "tradingAmount": 18904728,
      "transactionCount": 357
    },
    {
      "tradeDate": "2025-12-26",
      "open": 98,
      "high": 98.8,
      "low": 98,
      "close": 98.5,
      "change": 0.6,
      "volume": 114551,
      "tradingAmount": 11266305,
      "transactionCount": 320
    },
    {
      "tradeDate": "2025-12-29",
      "open": 98.5,
      "high": 100.5,
      "low": 98.5,
      "close": 99.6,
      "change": 1.1,
      "volume": 236974,
      "tradingAmount": 23611596,
      "transactionCount": 442
    },
    {
      "tradeDate": "2025-12-30",
      "open": 99.8,
      "high": 100,
      "low": 98.3,
      "close": 98.4,
      "change": -1.2,
      "volume": 256984,
      "tradingAmount": 25428903,
      "transactionCount": 447
    },
    {
      "tradeDate": "2025-12-31",
      "open": 98.5,
      "high": 98.5,
      "low": 97.5,
      "close": 97.6,
      "change": -0.8,
      "volume": 210782,
      "tradingAmount": 20628549,
      "transactionCount": 691
    },
    {
      "tradeDate": "2026-01-02",
      "open": 97.7,
      "high": 98,
      "low": 95.3,
      "close": 95.7,
      "change": -1.9,
      "volume": 667064,
      "tradingAmount": 64185256,
      "transactionCount": 1521
    },
    {
      "tradeDate": "2026-01-05",
      "open": 95.7,
      "high": 96.1,
      "low": 93.5,
      "close": 94,
      "change": -1.7,
      "volume": 1063732,
      "tradingAmount": 100140993,
      "transactionCount": 2109
    },
    {
      "tradeDate": "2026-01-06",
      "open": 94,
      "high": 95,
      "low": 93.6,
      "close": 95,
      "change": 1,
      "volume": 352756,
      "tradingAmount": 33216099,
      "transactionCount": 925
    },
    {
      "tradeDate": "2026-01-07",
      "open": 95,
      "high": 95,
      "low": 94,
      "close": 94,
      "change": -1,
      "volume": 278254,
      "tradingAmount": 26223223,
      "transactionCount": 754
    },
    {
      "tradeDate": "2026-01-08",
      "open": 94,
      "high": 95,
      "low": 94,
      "close": 94.6,
      "change": 0.6,
      "volume": 155459,
      "tradingAmount": 14728406,
      "transactionCount": 387
    },
    {
      "tradeDate": "2026-01-09",
      "open": 94.8,
      "high": 95.5,
      "low": 94.2,
      "close": 95.5,
      "change": 0.9,
      "volume": 199298,
      "tradingAmount": 18957067,
      "transactionCount": 382
    },
    {
      "tradeDate": "2026-01-12",
      "open": 95.5,
      "high": 95.5,
      "low": 94.2,
      "close": 94.3,
      "change": -1.2,
      "volume": 302808,
      "tradingAmount": 28615422,
      "transactionCount": 989
    },
    {
      "tradeDate": "2026-01-13",
      "open": 94.3,
      "high": 94.3,
      "low": 93.4,
      "close": 94.3,
      "change": 0,
      "volume": 407352,
      "tradingAmount": 38215101,
      "transactionCount": 1004
    },
    {
      "tradeDate": "2026-01-14",
      "open": 94.6,
      "high": 95.4,
      "low": 94.3,
      "close": 94.9,
      "change": 0.6,
      "volume": 303353,
      "tradingAmount": 28790055,
      "transactionCount": 928
    },
    {
      "tradeDate": "2026-01-15",
      "open": 95,
      "high": 95.7,
      "low": 94,
      "close": 95.7,
      "change": 0.8,
      "volume": 203866,
      "tradingAmount": 19452740,
      "transactionCount": 691
    },
    {
      "tradeDate": "2026-01-16",
      "open": 95.5,
      "high": 96.4,
      "low": 94.7,
      "close": 94.9,
      "change": -0.8,
      "volume": 380676,
      "tradingAmount": 36266296,
      "transactionCount": 1988
    },
    {
      "tradeDate": "2026-01-19",
      "open": 94.9,
      "high": 95,
      "low": 94,
      "close": 94.2,
      "change": -0.7,
      "volume": 342752,
      "tradingAmount": 32374919,
      "transactionCount": 1057
    },
    {
      "tradeDate": "2026-01-20",
      "open": 94.1,
      "high": 94.3,
      "low": 93.3,
      "close": 93.9,
      "change": -0.3,
      "volume": 570174,
      "tradingAmount": 53482371,
      "transactionCount": 1867
    },
    {
      "tradeDate": "2026-01-21",
      "open": 93.5,
      "high": 93.9,
      "low": 93,
      "close": 93.9,
      "change": 0,
      "volume": 328703,
      "tradingAmount": 30717007,
      "transactionCount": 874
    },
    {
      "tradeDate": "2026-01-22",
      "open": 93.7,
      "high": 94.2,
      "low": 93.7,
      "close": 94.2,
      "change": 0.3,
      "volume": 256510,
      "tradingAmount": 24097267,
      "transactionCount": 592
    },
    {
      "tradeDate": "2026-01-23",
      "open": 95.2,
      "high": 95.5,
      "low": 94.1,
      "close": 94.6,
      "change": 0.4,
      "volume": 286342,
      "tradingAmount": 27118078,
      "transactionCount": 495
    },
    {
      "tradeDate": "2026-01-26",
      "open": 94.9,
      "high": 95.7,
      "low": 94.6,
      "close": 95,
      "change": 0.4,
      "volume": 278062,
      "tradingAmount": 26453412,
      "transactionCount": 839
    },
    {
      "tradeDate": "2026-01-27",
      "open": 96,
      "high": 97.4,
      "low": 95.2,
      "close": 95.2,
      "change": 0.2,
      "volume": 380584,
      "tradingAmount": 36554420,
      "transactionCount": 2129
    },
    {
      "tradeDate": "2026-01-28",
      "open": 95.3,
      "high": 95.3,
      "low": 93.8,
      "close": 94.5,
      "change": -0.7,
      "volume": 360775,
      "tradingAmount": 34004809,
      "transactionCount": 1046
    },
    {
      "tradeDate": "2026-01-29",
      "open": 94.5,
      "high": 95.6,
      "low": 94,
      "close": 95.5,
      "change": 1,
      "volume": 340953,
      "tradingAmount": 32404892,
      "transactionCount": 543
    },
    {
      "tradeDate": "2026-01-30",
      "open": 95.5,
      "high": 95.5,
      "low": 94.1,
      "close": 94.1,
      "change": -1.4,
      "volume": 348758,
      "tradingAmount": 33034563,
      "transactionCount": 1412
    },
    {
      "tradeDate": "2026-02-02",
      "open": 93.9,
      "high": 93.9,
      "low": 92.3,
      "close": 93.5,
      "change": -0.6,
      "volume": 514507,
      "tradingAmount": 47900037,
      "transactionCount": 1009
    },
    {
      "tradeDate": "2026-02-03",
      "open": 93.5,
      "high": 94.1,
      "low": 92.4,
      "close": 93.5,
      "change": 0,
      "volume": 298205,
      "tradingAmount": 27803124,
      "transactionCount": 1281
    },
    {
      "tradeDate": "2026-02-04",
      "open": 93,
      "high": 94.5,
      "low": 93,
      "close": 94.1,
      "change": 0.6,
      "volume": 169552,
      "tradingAmount": 15957056,
      "transactionCount": 700
    },
    {
      "tradeDate": "2026-02-05",
      "open": 94.1,
      "high": 95.5,
      "low": 94.1,
      "close": 94.4,
      "change": 0.3,
      "volume": 280624,
      "tradingAmount": 26601052,
      "transactionCount": 709
    },
    {
      "tradeDate": "2026-02-06",
      "open": 93.6,
      "high": 93.7,
      "low": 92,
      "close": 92.8,
      "change": -1.6,
      "volume": 556434,
      "tradingAmount": 51544771,
      "transactionCount": 1218
    },
    {
      "tradeDate": "2026-02-09",
      "open": 93.7,
      "high": 93.7,
      "low": 92.4,
      "close": 92.8,
      "change": 0,
      "volume": 182676,
      "tradingAmount": 16963033,
      "transactionCount": 611
    },
    {
      "tradeDate": "2026-02-10",
      "open": 92.6,
      "high": 93.4,
      "low": 91.9,
      "close": 92.8,
      "change": 0,
      "volume": 427322,
      "tradingAmount": 39460685,
      "transactionCount": 936
    },
    {
      "tradeDate": "2026-02-11",
      "open": 92.8,
      "high": 93.5,
      "low": 92.7,
      "close": 93.5,
      "change": 0.7,
      "volume": 332817,
      "tradingAmount": 30976393,
      "transactionCount": 673
    },
    {
      "tradeDate": "2026-02-23",
      "open": 93.5,
      "high": 93.9,
      "low": 91.6,
      "close": 91.8,
      "change": -1.7,
      "volume": 875583,
      "tradingAmount": 80834152,
      "transactionCount": 2221
    },
    {
      "tradeDate": "2026-02-24",
      "open": 92.1,
      "high": 92.6,
      "low": 90.1,
      "close": 90.4,
      "change": -1.4,
      "volume": 826094,
      "tradingAmount": 74898692,
      "transactionCount": 2692
    },
    {
      "tradeDate": "2026-02-25",
      "open": 90.4,
      "high": 90.4,
      "low": 87.7,
      "close": 87.9,
      "change": -2.5,
      "volume": 1955776,
      "tradingAmount": 173121870,
      "transactionCount": 5012
    },
    {
      "tradeDate": "2026-02-26",
      "open": 88.1,
      "high": 88.8,
      "low": 86.5,
      "close": 86.5,
      "change": -1.4,
      "volume": 1122431,
      "tradingAmount": 97458999,
      "transactionCount": 2550
    },
    {
      "tradeDate": "2026-03-02",
      "open": 86.5,
      "high": 86.5,
      "low": 84.6,
      "close": 85.8,
      "change": -0.7,
      "volume": 688717,
      "tradingAmount": 59124678,
      "transactionCount": 2020
    },
    {
      "tradeDate": "2026-03-03",
      "open": 85.3,
      "high": 85.9,
      "low": 84.9,
      "close": 85.4,
      "change": -0.4,
      "volume": 451204,
      "tradingAmount": 38565294,
      "transactionCount": 1059
    },
    {
      "tradeDate": "2026-03-04",
      "open": 85,
      "high": 85,
      "low": 82.5,
      "close": 82.7,
      "change": -2.7,
      "volume": 947508,
      "tradingAmount": 79005698,
      "transactionCount": 2269
    },
    {
      "tradeDate": "2026-03-05",
      "open": 82.6,
      "high": 83.6,
      "low": 81.3,
      "close": 81.7,
      "change": -1,
      "volume": 1082415,
      "tradingAmount": 88758508,
      "transactionCount": 2127
    },
    {
      "tradeDate": "2026-03-06",
      "open": 81.5,
      "high": 84.8,
      "low": 80.5,
      "close": 84.5,
      "change": 2.8,
      "volume": 661213,
      "tradingAmount": 54776145,
      "transactionCount": 1111
    },
    {
      "tradeDate": "2026-03-09",
      "open": 82.9,
      "high": 82.9,
      "low": 81.1,
      "close": 81.7,
      "change": -2.8,
      "volume": 537618,
      "tradingAmount": 44034967,
      "transactionCount": 1219
    },
    {
      "tradeDate": "2026-03-10",
      "open": 82,
      "high": 84,
      "low": 82,
      "close": 83.5,
      "change": 1.8,
      "volume": 254652,
      "tradingAmount": 21180055,
      "transactionCount": 550
    },
    {
      "tradeDate": "2026-03-11",
      "open": 86.4,
      "high": 89.4,
      "low": 86.4,
      "close": 88.4,
      "change": 4.9,
      "volume": 995174,
      "tradingAmount": 87767561,
      "transactionCount": 1894
    },
    {
      "tradeDate": "2026-03-12",
      "open": 88.7,
      "high": 88.8,
      "low": 87.1,
      "close": 88,
      "change": -0.4,
      "volume": 393793,
      "tradingAmount": 34627695,
      "transactionCount": 1012
    },
    {
      "tradeDate": "2026-03-13",
      "open": 88,
      "high": 90,
      "low": 87.3,
      "close": 89.3,
      "change": 1.3,
      "volume": 582267,
      "tradingAmount": 51769992,
      "transactionCount": 807
    },
    {
      "tradeDate": "2026-03-16",
      "open": 89.3,
      "high": 91,
      "low": 89.3,
      "close": 90.5,
      "change": 1.2,
      "volume": 588708,
      "tradingAmount": 53302772,
      "transactionCount": 916
    },
    {
      "tradeDate": "2026-03-17",
      "open": 90.8,
      "high": 92,
      "low": 89.2,
      "close": 89.4,
      "change": -1.1,
      "volume": 660289,
      "tradingAmount": 59816008,
      "transactionCount": 1074
    },
    {
      "tradeDate": "2026-03-18",
      "open": 90,
      "high": 90.5,
      "low": 89,
      "close": 90.5,
      "change": 1.1,
      "volume": 365552,
      "tradingAmount": 32783460,
      "transactionCount": 619
    },
    {
      "tradeDate": "2026-03-19",
      "open": 90,
      "high": 91.4,
      "low": 89.3,
      "close": 91,
      "change": 0.5,
      "volume": 269152,
      "tradingAmount": 24299835,
      "transactionCount": 1716
    },
    {
      "tradeDate": "2026-03-20",
      "open": 90.5,
      "high": 91.8,
      "low": 89.4,
      "close": 89.8,
      "change": -1.2,
      "volume": 330579,
      "tradingAmount": 29987590,
      "transactionCount": 1853
    },
    {
      "tradeDate": "2026-03-23",
      "open": 87.7,
      "high": 90.3,
      "low": 86.7,
      "close": 89.6,
      "change": -0.2,
      "volume": 340237,
      "tradingAmount": 30311623,
      "transactionCount": 710
    },
    {
      "tradeDate": "2026-03-24",
      "open": 89.8,
      "high": 90.8,
      "low": 89.8,
      "close": 90.2,
      "change": 0.6,
      "volume": 155104,
      "tradingAmount": 13999465,
      "transactionCount": 795
    },
    {
      "tradeDate": "2026-03-25",
      "open": 91.8,
      "high": 91.8,
      "low": 89.7,
      "close": 91.6,
      "change": 1.4,
      "volume": 359803,
      "tradingAmount": 32799942,
      "transactionCount": 865
    },
    {
      "tradeDate": "2026-03-26",
      "open": 92.3,
      "high": 93,
      "low": 91.9,
      "close": 92.8,
      "change": 1.2,
      "volume": 373205,
      "tradingAmount": 34575934,
      "transactionCount": 912
    },
    {
      "tradeDate": "2026-03-27",
      "open": 92.7,
      "high": 93.3,
      "low": 92.1,
      "close": 92.2,
      "change": -0.6,
      "volume": 310228,
      "tradingAmount": 28748916,
      "transactionCount": 1465
    },
    {
      "tradeDate": "2026-03-30",
      "open": 90.9,
      "high": 92.5,
      "low": 90.6,
      "close": 91.7,
      "change": -0.5,
      "volume": 266890,
      "tradingAmount": 24512337,
      "transactionCount": 681
    },
    {
      "tradeDate": "2026-03-31",
      "open": 91,
      "high": 92.6,
      "low": 91,
      "close": 92.3,
      "change": 0.6,
      "volume": 258527,
      "tradingAmount": 23739989,
      "transactionCount": 490
    },
    {
      "tradeDate": "2026-04-01",
      "open": 93.2,
      "high": 93.4,
      "low": 92,
      "close": 93.1,
      "change": 0.8,
      "volume": 313506,
      "tradingAmount": 29121826,
      "transactionCount": 677
    },
    {
      "tradeDate": "2026-04-02",
      "open": 92.9,
      "high": 93,
      "low": 92.2,
      "close": 92.8,
      "change": -0.3,
      "volume": 166513,
      "tradingAmount": 15444132,
      "transactionCount": 371
    },
    {
      "tradeDate": "2026-04-07",
      "open": 93,
      "high": 93.3,
      "low": 92.2,
      "close": 93.2,
      "change": 0.4,
      "volume": 328560,
      "tradingAmount": 30484033,
      "transactionCount": 1391
    },
    {
      "tradeDate": "2026-04-08",
      "open": 93.4,
      "high": 93.8,
      "low": 92.6,
      "close": 93,
      "change": -0.2,
      "volume": 338808,
      "tradingAmount": 31525991,
      "transactionCount": 1667
    },
    {
      "tradeDate": "2026-04-09",
      "open": 92.9,
      "high": 92.9,
      "low": 92,
      "close": 92.3,
      "change": -0.7,
      "volume": 233205,
      "tradingAmount": 21528484,
      "transactionCount": 1230
    },
    {
      "tradeDate": "2026-04-10",
      "open": 92.8,
      "high": 93,
      "low": 90.8,
      "close": 91.1,
      "change": -1.2,
      "volume": 426383,
      "tradingAmount": 39040774,
      "transactionCount": 3039
    },
    {
      "tradeDate": "2026-04-13",
      "open": 91,
      "high": 91,
      "low": 89.6,
      "close": 90.1,
      "change": -1,
      "volume": 367972,
      "tradingAmount": 33129233,
      "transactionCount": 839
    },
    {
      "tradeDate": "2026-04-14",
      "open": 90,
      "high": 90,
      "low": 89.3,
      "close": 89.5,
      "change": -0.6,
      "volume": 526326,
      "tradingAmount": 47150606,
      "transactionCount": 1045
    },
    {
      "tradeDate": "2026-04-15",
      "open": 90,
      "high": 90.3,
      "low": 89.4,
      "close": 89.6,
      "change": 0.1,
      "volume": 233825,
      "tradingAmount": 21019243,
      "transactionCount": 479
    },
    {
      "tradeDate": "2026-04-16",
      "open": 89.9,
      "high": 90.9,
      "low": 89.9,
      "close": 90.4,
      "change": 0.8,
      "volume": 236114,
      "tradingAmount": 21347075,
      "transactionCount": 1162
    },
    {
      "tradeDate": "2026-04-17",
      "open": 90.8,
      "high": 90.8,
      "low": 90,
      "close": 90.2,
      "change": -0.2,
      "volume": 192393,
      "tradingAmount": 17361887,
      "transactionCount": 451
    },
    {
      "tradeDate": "2026-04-20",
      "open": 90.3,
      "high": 91.3,
      "low": 89,
      "close": 89.1,
      "change": -1.1,
      "volume": 523774,
      "tradingAmount": 46886849,
      "transactionCount": 1120
    },
    {
      "tradeDate": "2026-04-21",
      "open": 89.1,
      "high": 89.4,
      "low": 88.7,
      "close": 88.7,
      "change": -0.4,
      "volume": 459749,
      "tradingAmount": 40918936,
      "transactionCount": 954
    },
    {
      "tradeDate": "2026-04-22",
      "open": 90,
      "high": 90,
      "low": 88.8,
      "close": 88.9,
      "change": 0.2,
      "volume": 278453,
      "tradingAmount": 24796077,
      "transactionCount": 573
    },
    {
      "tradeDate": "2026-04-23",
      "open": 88.9,
      "high": 88.9,
      "low": 87.5,
      "close": 88.4,
      "change": -0.5,
      "volume": 483452,
      "tradingAmount": 42575098,
      "transactionCount": 1153
    },
    {
      "tradeDate": "2026-04-24",
      "open": 88.4,
      "high": 88.4,
      "low": 86.6,
      "close": 86.9,
      "change": -1.5,
      "volume": 487718,
      "tradingAmount": 42568627,
      "transactionCount": 1205
    },
    {
      "tradeDate": "2026-04-27",
      "open": 86.8,
      "high": 86.8,
      "low": 85.1,
      "close": 85.9,
      "change": -1,
      "volume": 602780,
      "tradingAmount": 51594999,
      "transactionCount": 1342
    },
    {
      "tradeDate": "2026-04-28",
      "open": 85.9,
      "high": 87.4,
      "low": 85.5,
      "close": 87,
      "change": 1.1,
      "volume": 282180,
      "tradingAmount": 24431273,
      "transactionCount": 899
    },
    {
      "tradeDate": "2026-04-29",
      "open": 87.5,
      "high": 88,
      "low": 86.8,
      "close": 87.6,
      "change": 0.6,
      "volume": 189723,
      "tradingAmount": 16572757,
      "transactionCount": 534
    },
    {
      "tradeDate": "2026-04-30",
      "open": 87.5,
      "high": 87.6,
      "low": 86.8,
      "close": 86.8,
      "change": -0.8,
      "volume": 249240,
      "tradingAmount": 21682091,
      "transactionCount": 1390
    },
    {
      "tradeDate": "2026-05-04",
      "open": 86.8,
      "high": 87.2,
      "low": 86.5,
      "close": 87,
      "change": 0.2,
      "volume": 296874,
      "tradingAmount": 25800338,
      "transactionCount": 637
    },
    {
      "tradeDate": "2026-05-05",
      "open": 87.2,
      "high": 88.3,
      "low": 86.6,
      "close": 87.3,
      "change": 0.3,
      "volume": 212339,
      "tradingAmount": 18466797,
      "transactionCount": 1371
    },
    {
      "tradeDate": "2026-05-06",
      "open": 88,
      "high": 88,
      "low": 86.4,
      "close": 86.8,
      "change": -0.5,
      "volume": 487004,
      "tradingAmount": 42279965,
      "transactionCount": 1900
    },
    {
      "tradeDate": "2026-05-07",
      "open": 86.5,
      "high": 86.7,
      "low": 85.3,
      "close": 86.7,
      "change": -0.1,
      "volume": 696874,
      "tradingAmount": 59774204,
      "transactionCount": 1329
    },
    {
      "tradeDate": "2026-05-08",
      "open": 86.7,
      "high": 88,
      "low": 86.4,
      "close": 86.5,
      "change": -0.2,
      "volume": 308676,
      "tradingAmount": 26812319,
      "transactionCount": 602
    },
    {
      "tradeDate": "2026-05-11",
      "open": 86.5,
      "high": 87.3,
      "low": 86.5,
      "close": 87,
      "change": 0.5,
      "volume": 276520,
      "tradingAmount": 24059194,
      "transactionCount": 535
    },
    {
      "tradeDate": "2026-05-12",
      "open": 87,
      "high": 87,
      "low": 85.9,
      "close": 86.3,
      "change": -0.7,
      "volume": 286616,
      "tradingAmount": 24727987,
      "transactionCount": 993
    },
    {
      "tradeDate": "2026-05-13",
      "open": 86.6,
      "high": 86.6,
      "low": 85.2,
      "close": 86.1,
      "change": -0.2,
      "volume": 443430,
      "tradingAmount": 38007744,
      "transactionCount": 906
    },
    {
      "tradeDate": "2026-05-14",
      "open": 85.7,
      "high": 86.6,
      "low": 85.7,
      "close": 85.8,
      "change": -0.3,
      "volume": 261328,
      "tradingAmount": 22492982,
      "transactionCount": 501
    },
    {
      "tradeDate": "2026-05-15",
      "open": 86.6,
      "high": 86.6,
      "low": 85.3,
      "close": 85.5,
      "change": -0.3,
      "volume": 220191,
      "tradingAmount": 18913197,
      "transactionCount": 538
    },
    {
      "tradeDate": "2026-05-18",
      "open": 85.4,
      "high": 86.6,
      "low": 84.6,
      "close": 86,
      "change": 0.5,
      "volume": 379159,
      "tradingAmount": 32425230,
      "transactionCount": 626
    },
    {
      "tradeDate": "2026-05-19",
      "open": 85.9,
      "high": 87.6,
      "low": 85.9,
      "close": 87.4,
      "change": 1.4,
      "volume": 396249,
      "tradingAmount": 34579328,
      "transactionCount": 829
    },
    {
      "tradeDate": "2026-05-20",
      "open": 87.4,
      "high": 87.8,
      "low": 86.2,
      "close": 86.6,
      "change": -0.8,
      "volume": 289293,
      "tradingAmount": 25076492,
      "transactionCount": 1016
    },
    {
      "tradeDate": "2026-05-21",
      "open": 86.2,
      "high": 86.8,
      "low": 86,
      "close": 86.8,
      "change": 0.2,
      "volume": 245032,
      "tradingAmount": 21134892,
      "transactionCount": 498
    },
    {
      "tradeDate": "2026-05-22",
      "open": 86.6,
      "high": 86.6,
      "low": 85.8,
      "close": 85.8,
      "change": -1,
      "volume": 302628,
      "tradingAmount": 26057581,
      "transactionCount": 632
    },
    {
      "tradeDate": "2026-05-25",
      "open": 85.5,
      "high": 85.5,
      "low": 84.1,
      "close": 84.8,
      "change": -1,
      "volume": 673581,
      "tradingAmount": 56942381,
      "transactionCount": 1498
    },
    {
      "tradeDate": "2026-05-26",
      "open": 84.8,
      "high": 85.8,
      "low": 84.8,
      "close": 85.6,
      "change": 0.8,
      "volume": 317762,
      "tradingAmount": 27086097,
      "transactionCount": 581
    },
    {
      "tradeDate": "2026-05-27",
      "open": 85.3,
      "high": 86.1,
      "low": 85,
      "close": 85.6,
      "change": 0,
      "volume": 488937,
      "tradingAmount": 41826740,
      "transactionCount": 1190
    },
    {
      "tradeDate": "2026-05-28",
      "open": 85.6,
      "high": 86.4,
      "low": 84.6,
      "close": 84.7,
      "change": -0.9,
      "volume": 437541,
      "tradingAmount": 37252749,
      "transactionCount": 924
    },
    {
      "tradeDate": "2026-05-29",
      "open": 84.8,
      "high": 86,
      "low": 84.8,
      "close": 85.5,
      "change": 0.8,
      "volume": 396387,
      "tradingAmount": 33882154,
      "transactionCount": 495
    },
    {
      "tradeDate": "2026-06-01",
      "open": 85.8,
      "high": 86.2,
      "low": 84.7,
      "close": 86,
      "change": 0.5,
      "volume": 574361,
      "tradingAmount": 49076039,
      "transactionCount": 912
    },
    {
      "tradeDate": "2026-06-02",
      "open": 85.8,
      "high": 86.2,
      "low": 85.3,
      "close": 86.1,
      "change": 0.1,
      "volume": 367777,
      "tradingAmount": 31542388,
      "transactionCount": 636
    },
    {
      "tradeDate": "2026-06-03",
      "open": 86.3,
      "high": 87.5,
      "low": 85.8,
      "close": 86.7,
      "change": 0.6,
      "volume": 486204,
      "tradingAmount": 42198023,
      "transactionCount": 853
    },
    {
      "tradeDate": "2026-06-04",
      "open": 87.2,
      "high": 87.2,
      "low": 86.1,
      "close": 86.9,
      "change": 0.2,
      "volume": 255113,
      "tradingAmount": 22133130,
      "transactionCount": 834
    },
    {
      "tradeDate": "2026-06-05",
      "open": 86.9,
      "high": 89.4,
      "low": 86.9,
      "close": 89,
      "change": 2.1,
      "volume": 668152,
      "tradingAmount": 59231839,
      "transactionCount": 997
    },
    {
      "tradeDate": "2026-06-08",
      "open": 87.1,
      "high": 87.7,
      "low": 86,
      "close": 86.7,
      "change": -2.3,
      "volume": 466461,
      "tradingAmount": 40503831,
      "transactionCount": 764
    },
    {
      "tradeDate": "2026-06-09",
      "open": 86.7,
      "high": 88.8,
      "low": 86.7,
      "close": 87.2,
      "change": 0.5,
      "volume": 323685,
      "tradingAmount": 28411251,
      "transactionCount": 541
    },
    {
      "tradeDate": "2026-06-10",
      "open": 87.2,
      "high": 87.8,
      "low": 86.4,
      "close": 87.1,
      "change": -0.1,
      "volume": 279071,
      "tradingAmount": 24311545,
      "transactionCount": 500
    },
    {
      "tradeDate": "2026-06-11",
      "open": 87.9,
      "high": 87.9,
      "low": 86.7,
      "close": 87.2,
      "change": 0.1,
      "volume": 232079,
      "tradingAmount": 20227400,
      "transactionCount": 362
    },
    {
      "tradeDate": "2026-06-12",
      "open": 87.5,
      "high": 89.5,
      "low": 87.5,
      "close": 89.1,
      "change": 1.9,
      "volume": 371992,
      "tradingAmount": 33030158,
      "transactionCount": 579
    },
    {
      "tradeDate": "2026-06-15",
      "open": 89.4,
      "high": 89.4,
      "low": 87.3,
      "close": 87.6,
      "change": -1.5,
      "volume": 568444,
      "tradingAmount": 50026058,
      "transactionCount": 984
    },
    {
      "tradeDate": "2026-06-16",
      "open": 88.4,
      "high": 88.4,
      "low": 86.9,
      "close": 87.4,
      "change": -0.2,
      "volume": 236443,
      "tradingAmount": 20658920,
      "transactionCount": 437
    },
    {
      "tradeDate": "2026-06-17",
      "open": 87.3,
      "high": 87.8,
      "low": 86.7,
      "close": 87,
      "change": -0.4,
      "volume": 271569,
      "tradingAmount": 23641931,
      "transactionCount": 575
    },
    {
      "tradeDate": "2026-06-18",
      "open": 87,
      "high": 87.4,
      "low": 86.8,
      "close": 87.4,
      "change": 0.4,
      "volume": 221027,
      "tradingAmount": 19255848,
      "transactionCount": 326
    },
    {
      "tradeDate": "2026-06-22",
      "open": 87.4,
      "high": 87.4,
      "low": 86.5,
      "close": 86.8,
      "change": -0.6,
      "volume": 359188,
      "tradingAmount": 31159356,
      "transactionCount": 685
    },
    {
      "tradeDate": "2026-06-23",
      "open": 87,
      "high": 88,
      "low": 86.8,
      "close": 88,
      "change": 1.2,
      "volume": 356354,
      "tradingAmount": 31207397,
      "transactionCount": 497
    },
    {
      "tradeDate": "2026-06-24",
      "open": 88.1,
      "high": 88.5,
      "low": 87.2,
      "close": 88,
      "change": 0,
      "volume": 364108,
      "tradingAmount": 32011477,
      "transactionCount": 503
    },
    {
      "tradeDate": "2026-06-25",
      "open": 88,
      "high": 88.9,
      "low": 87.9,
      "close": 88.1,
      "change": 0.1,
      "volume": 319881,
      "tradingAmount": 28327032,
      "transactionCount": 476
    },
    {
      "tradeDate": "2026-06-26",
      "open": 87.7,
      "high": 88.2,
      "low": 86.8,
      "close": 87.1,
      "change": -1,
      "volume": 326825,
      "tradingAmount": 28532453,
      "transactionCount": 667
    },
    {
      "tradeDate": "2026-06-29",
      "open": 88,
      "high": 88.2,
      "low": 87.7,
      "close": 88.1,
      "change": 1,
      "volume": 276548,
      "tradingAmount": 24331496,
      "transactionCount": 402
    },
    {
      "tradeDate": "2026-06-30",
      "open": 88.1,
      "high": 88.2,
      "low": 87,
      "close": 87.1,
      "change": -1,
      "volume": 369868,
      "tradingAmount": 32299432,
      "transactionCount": 559
    },
    {
      "tradeDate": "2026-07-01",
      "open": 87.3,
      "high": 88.2,
      "low": 86.5,
      "close": 88.2,
      "change": 1.1,
      "volume": 358621,
      "tradingAmount": 31479253,
      "transactionCount": 453
    },
    {
      "tradeDate": "2026-07-02",
      "open": 88,
      "high": 88.3,
      "low": 87.4,
      "close": 87.9,
      "change": -0.3,
      "volume": 239778,
      "tradingAmount": 21044436,
      "transactionCount": 890
    },
    {
      "tradeDate": "2026-07-03",
      "open": 87.4,
      "high": 89.2,
      "low": 87.4,
      "close": 88.5,
      "change": 0.6,
      "volume": 324518,
      "tradingAmount": 28774171,
      "transactionCount": 456
    },
    {
      "tradeDate": "2026-07-06",
      "open": 88.5,
      "high": 89.9,
      "low": 88.1,
      "close": 89.1,
      "change": 0.6,
      "volume": 410006,
      "tradingAmount": 36536953,
      "transactionCount": 576
    },
    {
      "tradeDate": "2026-07-07",
      "open": 89.2,
      "high": 89.5,
      "low": 88.1,
      "close": 88.3,
      "change": -0.8,
      "volume": 396363,
      "tradingAmount": 35187758,
      "transactionCount": 621
    },
    {
      "tradeDate": "2026-07-08",
      "open": 87.9,
      "high": 88.2,
      "low": 86.5,
      "close": 86.7,
      "change": -1.6,
      "volume": 603963,
      "tradingAmount": 52554399,
      "transactionCount": 968
    },
    {
      "tradeDate": "2026-07-09",
      "open": 86,
      "high": 86.6,
      "low": 85.8,
      "close": 86.4,
      "change": -0.3,
      "volume": 452550,
      "tradingAmount": 38990871,
      "transactionCount": 697
    },
    {
      "tradeDate": "2026-07-13",
      "open": 86,
      "high": 86.5,
      "low": 85.5,
      "close": 86.5,
      "change": 0.1,
      "volume": 343812,
      "tradingAmount": 29577498,
      "transactionCount": 549
    },
    {
      "tradeDate": "2026-07-14",
      "open": 87.5,
      "high": 87.5,
      "low": 85.1,
      "close": 85.8,
      "change": -0.7,
      "volume": 431708,
      "tradingAmount": 37014891,
      "transactionCount": 802
    },
    {
      "tradeDate": "2026-07-15",
      "open": 87.1,
      "high": 88.4,
      "low": 86.4,
      "close": 88.2,
      "change": 2.4,
      "volume": 311782,
      "tradingAmount": 27249515,
      "transactionCount": 450
    },
    {
      "tradeDate": "2026-07-16",
      "open": 88.5,
      "high": 91.9,
      "low": 88.5,
      "close": 91.9,
      "change": 3.7,
      "volume": 1032776,
      "tradingAmount": 93841580,
      "transactionCount": 1374
    }
  ]
}
