{
  "schemaVersion": "1.0",
  "symbol": "2013",
  "name": "中鋼構",
  "market": "TWSE",
  "source": "TWSE",
  "sourceUrl": "https://www.twse.com.tw/rwd/zh/afterTrading/STOCK_DAY",
  "fetchedAt": "2026-07-22T01:59:00.555Z",
  "firstTradeDate": "2025-04-01",
  "lastTradeDate": "2026-07-21",
  "recordCount": 318,
  "status": "official",
  "warnings": [],
  "prices": [
    {
      "tradeDate": "2025-04-01",
      "open": 48.95,
      "high": 49.5,
      "low": 48.85,
      "close": 49.1,
      "change": 0.4,
      "volume": 101296,
      "tradingAmount": 4975314,
      "transactionCount": 236
    },
    {
      "tradeDate": "2025-04-02",
      "open": 48.3,
      "high": 49.35,
      "low": 48.3,
      "close": 49.1,
      "change": 0,
      "volume": 73684,
      "tradingAmount": 3610981,
      "transactionCount": 158
    },
    {
      "tradeDate": "2025-04-07",
      "open": 44.2,
      "high": 46.15,
      "low": 44.2,
      "close": 44.3,
      "change": -4.8,
      "volume": 398170,
      "tradingAmount": 17780886,
      "transactionCount": 806
    },
    {
      "tradeDate": "2025-04-08",
      "open": 44.45,
      "high": 44.7,
      "low": 43.15,
      "close": 43.7,
      "change": -0.6,
      "volume": 191181,
      "tradingAmount": 8366841,
      "transactionCount": 480
    },
    {
      "tradeDate": "2025-04-09",
      "open": 43.85,
      "high": 43.85,
      "low": 39.55,
      "close": 39.8,
      "change": -3.9,
      "volume": 434124,
      "tradingAmount": 17886185,
      "transactionCount": 816
    },
    {
      "tradeDate": "2025-04-10",
      "open": 43,
      "high": 43.75,
      "low": 42.95,
      "close": 43.75,
      "change": 3.95,
      "volume": 400442,
      "tradingAmount": 17338213,
      "transactionCount": 315
    },
    {
      "tradeDate": "2025-04-11",
      "open": 43.75,
      "high": 44.85,
      "low": 42.2,
      "close": 43.95,
      "change": 0.2,
      "volume": 137994,
      "tradingAmount": 6039150,
      "transactionCount": 313
    },
    {
      "tradeDate": "2025-04-14",
      "open": 44.3,
      "high": 45.15,
      "low": 44,
      "close": 44,
      "change": 0.05,
      "volume": 115525,
      "tradingAmount": 5138221,
      "transactionCount": 304
    },
    {
      "tradeDate": "2025-04-15",
      "open": 44.3,
      "high": 45.3,
      "low": 44.3,
      "close": 45,
      "change": 1,
      "volume": 62198,
      "tradingAmount": 2795216,
      "transactionCount": 143
    },
    {
      "tradeDate": "2025-04-16",
      "open": 44.95,
      "high": 44.95,
      "low": 44.25,
      "close": 44.25,
      "change": -0.75,
      "volume": 64376,
      "tradingAmount": 2864029,
      "transactionCount": 271
    },
    {
      "tradeDate": "2025-04-17",
      "open": 43.9,
      "high": 44,
      "low": 43.65,
      "close": 43.95,
      "change": -0.3,
      "volume": 49448,
      "tradingAmount": 2168951,
      "transactionCount": 283
    },
    {
      "tradeDate": "2025-04-18",
      "open": 43.55,
      "high": 44.7,
      "low": 43.55,
      "close": 43.9,
      "change": -0.05,
      "volume": 30862,
      "tradingAmount": 1359756,
      "transactionCount": 128
    },
    {
      "tradeDate": "2025-04-21",
      "open": 43.95,
      "high": 44.8,
      "low": 43.4,
      "close": 43.75,
      "change": -0.15,
      "volume": 32030,
      "tradingAmount": 1399630,
      "transactionCount": 172
    },
    {
      "tradeDate": "2025-04-22",
      "open": 43.5,
      "high": 43.85,
      "low": 43.4,
      "close": 43.5,
      "change": -0.25,
      "volume": 51202,
      "tradingAmount": 2231432,
      "transactionCount": 117
    },
    {
      "tradeDate": "2025-04-23",
      "open": 43.6,
      "high": 44.15,
      "low": 43.6,
      "close": 43.75,
      "change": 0.25,
      "volume": 117496,
      "tradingAmount": 5140723,
      "transactionCount": 153
    },
    {
      "tradeDate": "2025-04-24",
      "open": 43.85,
      "high": 44.15,
      "low": 43.8,
      "close": 44,
      "change": 0.25,
      "volume": 18859,
      "tradingAmount": 829839,
      "transactionCount": 88
    },
    {
      "tradeDate": "2025-04-25",
      "open": 44.25,
      "high": 44.25,
      "low": 43.8,
      "close": 43.9,
      "change": -0.1,
      "volume": 78139,
      "tradingAmount": 3439415,
      "transactionCount": 155
    },
    {
      "tradeDate": "2025-04-28",
      "open": 43.75,
      "high": 43.9,
      "low": 43.75,
      "close": 43.85,
      "change": -0.05,
      "volume": 32153,
      "tradingAmount": 1410727,
      "transactionCount": 154
    },
    {
      "tradeDate": "2025-04-29",
      "open": 43.85,
      "high": 44.5,
      "low": 43.85,
      "close": 43.9,
      "change": 0.05,
      "volume": 110784,
      "tradingAmount": 4874417,
      "transactionCount": 250
    },
    {
      "tradeDate": "2025-04-30",
      "open": 43.9,
      "high": 44,
      "low": 43.7,
      "close": 43.7,
      "change": -0.2,
      "volume": 90983,
      "tradingAmount": 3993820,
      "transactionCount": 328
    },
    {
      "tradeDate": "2025-05-02",
      "open": 43.7,
      "high": 44.65,
      "low": 43.7,
      "close": 44.3,
      "change": 0.6,
      "volume": 47310,
      "tradingAmount": 2089606,
      "transactionCount": 128
    },
    {
      "tradeDate": "2025-05-05",
      "open": 44.5,
      "high": 44.5,
      "low": 43.55,
      "close": 43.95,
      "change": -0.35,
      "volume": 84372,
      "tradingAmount": 3704253,
      "transactionCount": 249
    },
    {
      "tradeDate": "2025-05-06",
      "open": 44.5,
      "high": 44.8,
      "low": 43.9,
      "close": 44,
      "change": 0.05,
      "volume": 81525,
      "tradingAmount": 3621169,
      "transactionCount": 143
    },
    {
      "tradeDate": "2025-05-07",
      "open": 43.95,
      "high": 44.45,
      "low": 43.75,
      "close": 43.85,
      "change": -0.15,
      "volume": 55373,
      "tradingAmount": 2438044,
      "transactionCount": 257
    },
    {
      "tradeDate": "2025-05-08",
      "open": 43.8,
      "high": 44.3,
      "low": 43.6,
      "close": 44,
      "change": 0.15,
      "volume": 91895,
      "tradingAmount": 4032905,
      "transactionCount": 244
    },
    {
      "tradeDate": "2025-05-09",
      "open": 43.9,
      "high": 44.2,
      "low": 43.9,
      "close": 44,
      "change": 0,
      "volume": 204674,
      "tradingAmount": 9017422,
      "transactionCount": 222
    },
    {
      "tradeDate": "2025-05-12",
      "open": 44.85,
      "high": 44.85,
      "low": 44.05,
      "close": 44.5,
      "change": 0.5,
      "volume": 109355,
      "tradingAmount": 4845969,
      "transactionCount": 103
    },
    {
      "tradeDate": "2025-05-13",
      "open": 44.55,
      "high": 44.8,
      "low": 44.35,
      "close": 44.5,
      "change": 0,
      "volume": 134951,
      "tradingAmount": 6017391,
      "transactionCount": 207
    },
    {
      "tradeDate": "2025-05-14",
      "open": 44.9,
      "high": 45,
      "low": 44.45,
      "close": 44.9,
      "change": 0.4,
      "volume": 231520,
      "tradingAmount": 10351068,
      "transactionCount": 557
    },
    {
      "tradeDate": "2025-05-15",
      "open": 44.9,
      "high": 44.9,
      "low": 44.5,
      "close": 44.8,
      "change": -0.1,
      "volume": 74762,
      "tradingAmount": 3339276,
      "transactionCount": 176
    },
    {
      "tradeDate": "2025-05-16",
      "open": 44.65,
      "high": 45.4,
      "low": 44.2,
      "close": 44.85,
      "change": 0.05,
      "volume": 188634,
      "tradingAmount": 8475525,
      "transactionCount": 250
    },
    {
      "tradeDate": "2025-05-19",
      "open": 44.5,
      "high": 44.85,
      "low": 44.35,
      "close": 44.35,
      "change": -0.5,
      "volume": 54603,
      "tradingAmount": 2436241,
      "transactionCount": 163
    },
    {
      "tradeDate": "2025-05-20",
      "open": 44.95,
      "high": 44.95,
      "low": 44.25,
      "close": 44.35,
      "change": 0,
      "volume": 142229,
      "tradingAmount": 6314542,
      "transactionCount": 157
    },
    {
      "tradeDate": "2025-05-21",
      "open": 44.6,
      "high": 44.9,
      "low": 44.35,
      "close": 44.4,
      "change": 0.05,
      "volume": 104871,
      "tradingAmount": 4670867,
      "transactionCount": 143
    },
    {
      "tradeDate": "2025-05-22",
      "open": 44.35,
      "high": 44.4,
      "low": 44,
      "close": 44.1,
      "change": -0.3,
      "volume": 73071,
      "tradingAmount": 3230856,
      "transactionCount": 249
    },
    {
      "tradeDate": "2025-05-23",
      "open": 43.6,
      "high": 44.4,
      "low": 43.6,
      "close": 44.4,
      "change": 0.3,
      "volume": 54152,
      "tradingAmount": 2385173,
      "transactionCount": 158
    },
    {
      "tradeDate": "2025-05-26",
      "open": 44,
      "high": 44.4,
      "low": 43.85,
      "close": 44,
      "change": -0.4,
      "volume": 123680,
      "tradingAmount": 5453624,
      "transactionCount": 278
    },
    {
      "tradeDate": "2025-05-27",
      "open": 43.85,
      "high": 44.4,
      "low": 43.65,
      "close": 43.7,
      "change": -0.3,
      "volume": 125909,
      "tradingAmount": 5521523,
      "transactionCount": 244
    },
    {
      "tradeDate": "2025-05-28",
      "open": 43.8,
      "high": 44.15,
      "low": 43.45,
      "close": 43.6,
      "change": -0.1,
      "volume": 84671,
      "tradingAmount": 3695058,
      "transactionCount": 160
    },
    {
      "tradeDate": "2025-05-29",
      "open": 43.75,
      "high": 44,
      "low": 43.3,
      "close": 43.85,
      "change": 0.25,
      "volume": 138785,
      "tradingAmount": 6034488,
      "transactionCount": 176
    },
    {
      "tradeDate": "2025-06-02",
      "open": 43.5,
      "high": 43.5,
      "low": 42.5,
      "close": 42.6,
      "change": -1.25,
      "volume": 110191,
      "tradingAmount": 4718969,
      "transactionCount": 278
    },
    {
      "tradeDate": "2025-06-03",
      "open": 42.75,
      "high": 42.95,
      "low": 42.25,
      "close": 42.4,
      "change": -0.2,
      "volume": 100249,
      "tradingAmount": 4267423,
      "transactionCount": 197
    },
    {
      "tradeDate": "2025-06-04",
      "open": 42.5,
      "high": 42.95,
      "low": 42.4,
      "close": 42.65,
      "change": 0.25,
      "volume": 83879,
      "tradingAmount": 3574911,
      "transactionCount": 122
    },
    {
      "tradeDate": "2025-06-05",
      "open": 42.65,
      "high": 43.3,
      "low": 42.65,
      "close": 43.15,
      "change": 0.5,
      "volume": 54931,
      "tradingAmount": 2365220,
      "transactionCount": 93
    },
    {
      "tradeDate": "2025-06-06",
      "open": 42.75,
      "high": 43.35,
      "low": 42.5,
      "close": 42.7,
      "change": -0.45,
      "volume": 93000,
      "tradingAmount": 3989153,
      "transactionCount": 262
    },
    {
      "tradeDate": "2025-06-09",
      "open": 43.1,
      "high": 43.1,
      "low": 41.85,
      "close": 41.9,
      "change": -0.8,
      "volume": 201042,
      "tradingAmount": 8481322,
      "transactionCount": 342
    },
    {
      "tradeDate": "2025-06-10",
      "open": 42.45,
      "high": 42.7,
      "low": 42,
      "close": 42.05,
      "change": 0.15,
      "volume": 163491,
      "tradingAmount": 6912336,
      "transactionCount": 306
    },
    {
      "tradeDate": "2025-06-11",
      "open": 42.2,
      "high": 42.25,
      "low": 41.5,
      "close": 41.8,
      "change": -0.25,
      "volume": 148408,
      "tradingAmount": 6218998,
      "transactionCount": 315
    },
    {
      "tradeDate": "2025-06-12",
      "open": 42.25,
      "high": 42.8,
      "low": 41.9,
      "close": 42,
      "change": 0.2,
      "volume": 107015,
      "tradingAmount": 4515322,
      "transactionCount": 184
    },
    {
      "tradeDate": "2025-06-13",
      "open": 41.9,
      "high": 42.55,
      "low": 41.9,
      "close": 42.3,
      "change": 0.3,
      "volume": 82580,
      "tradingAmount": 3492541,
      "transactionCount": 163
    },
    {
      "tradeDate": "2025-06-16",
      "open": 42.25,
      "high": 42.9,
      "low": 42.25,
      "close": 42.85,
      "change": 0.55,
      "volume": 49582,
      "tradingAmount": 2114852,
      "transactionCount": 77
    },
    {
      "tradeDate": "2025-06-17",
      "open": 42.9,
      "high": 42.95,
      "low": 42.6,
      "close": 42.7,
      "change": -0.15,
      "volume": 47120,
      "tradingAmount": 2013995,
      "transactionCount": 112
    },
    {
      "tradeDate": "2025-06-18",
      "open": 42.75,
      "high": 42.8,
      "low": 42.4,
      "close": 42.5,
      "change": -0.2,
      "volume": 50699,
      "tradingAmount": 2159703,
      "transactionCount": 111
    },
    {
      "tradeDate": "2025-06-19",
      "open": 42.3,
      "high": 42.4,
      "low": 41.9,
      "close": 42,
      "change": -0.5,
      "volume": 103666,
      "tradingAmount": 4369656,
      "transactionCount": 153
    },
    {
      "tradeDate": "2025-06-20",
      "open": 42.05,
      "high": 42.95,
      "low": 41.7,
      "close": 42.9,
      "change": 0.9,
      "volume": 140925,
      "tradingAmount": 5968704,
      "transactionCount": 145
    },
    {
      "tradeDate": "2025-06-23",
      "open": 43.4,
      "high": 43.4,
      "low": 42.1,
      "close": 42.45,
      "change": -0.45,
      "volume": 89695,
      "tradingAmount": 3806209,
      "transactionCount": 174
    },
    {
      "tradeDate": "2025-06-24",
      "open": 43.95,
      "high": 43.95,
      "low": 42.8,
      "close": 43.85,
      "change": 1.4,
      "volume": 137073,
      "tradingAmount": 5934923,
      "transactionCount": 147
    },
    {
      "tradeDate": "2025-06-25",
      "open": 43.8,
      "high": 44,
      "low": 43.25,
      "close": 43.8,
      "change": -0.05,
      "volume": 65297,
      "tradingAmount": 2855778,
      "transactionCount": 191
    },
    {
      "tradeDate": "2025-06-26",
      "open": 43.8,
      "high": 44.1,
      "low": 43.75,
      "close": 43.75,
      "change": -0.05,
      "volume": 72302,
      "tradingAmount": 3175473,
      "transactionCount": 108
    },
    {
      "tradeDate": "2025-06-27",
      "open": 43.7,
      "high": 43.9,
      "low": 43.45,
      "close": 43.45,
      "change": -0.3,
      "volume": 106692,
      "tradingAmount": 4650555,
      "transactionCount": 166
    },
    {
      "tradeDate": "2025-06-30",
      "open": 43.35,
      "high": 43.85,
      "low": 43.3,
      "close": 43.85,
      "change": 0.4,
      "volume": 43219,
      "tradingAmount": 1881021,
      "transactionCount": 71
    },
    {
      "tradeDate": "2025-07-01",
      "open": 44.1,
      "high": 44.9,
      "low": 43.95,
      "close": 44.5,
      "change": 0.65,
      "volume": 135583,
      "tradingAmount": 6028997,
      "transactionCount": 161
    },
    {
      "tradeDate": "2025-07-02",
      "open": 44.25,
      "high": 44.65,
      "low": 44.25,
      "close": 44.45,
      "change": -0.05,
      "volume": 26359,
      "tradingAmount": 1172470,
      "transactionCount": 136
    },
    {
      "tradeDate": "2025-07-03",
      "open": 44.4,
      "high": 44.8,
      "low": 44.4,
      "close": 44.65,
      "change": 0.2,
      "volume": 53537,
      "tradingAmount": 2390287,
      "transactionCount": 97
    },
    {
      "tradeDate": "2025-07-04",
      "open": 44.7,
      "high": 44.7,
      "low": 44.1,
      "close": 44.1,
      "change": -0.55,
      "volume": 88762,
      "tradingAmount": 3936775,
      "transactionCount": 208
    },
    {
      "tradeDate": "2025-07-07",
      "open": 44.15,
      "high": 44.15,
      "low": 43.45,
      "close": 43.45,
      "change": -0.65,
      "volume": 40472,
      "tradingAmount": 1767488,
      "transactionCount": 144
    },
    {
      "tradeDate": "2025-07-08",
      "open": 43.2,
      "high": 43.8,
      "low": 42.9,
      "close": 43.8,
      "change": 0.35,
      "volume": 73219,
      "tradingAmount": 3162546,
      "transactionCount": 128
    },
    {
      "tradeDate": "2025-07-09",
      "open": 43.5,
      "high": 43.7,
      "low": 43.5,
      "close": 43.6,
      "change": -0.2,
      "volume": 22912,
      "tradingAmount": 998903,
      "transactionCount": 68
    },
    {
      "tradeDate": "2025-07-10",
      "open": 43.35,
      "high": 43.85,
      "low": 43.05,
      "close": 43.65,
      "change": 0.05,
      "volume": 81923,
      "tradingAmount": 3575120,
      "transactionCount": 128
    },
    {
      "tradeDate": "2025-07-11",
      "open": 43.8,
      "high": 44.2,
      "low": 43.65,
      "close": 44,
      "change": 0.35,
      "volume": 163351,
      "tradingAmount": 7189643,
      "transactionCount": 249
    },
    {
      "tradeDate": "2025-07-14",
      "open": 42.05,
      "high": 42.8,
      "low": 42.05,
      "close": 42.1,
      "change": 0,
      "volume": 109587,
      "tradingAmount": 4619107,
      "transactionCount": 188
    },
    {
      "tradeDate": "2025-07-15",
      "open": 42.1,
      "high": 42.1,
      "low": 41.5,
      "close": 41.6,
      "change": -0.5,
      "volume": 280942,
      "tradingAmount": 11725303,
      "transactionCount": 464
    },
    {
      "tradeDate": "2025-07-16",
      "open": 41.6,
      "high": 42.25,
      "low": 41.6,
      "close": 41.95,
      "change": 0.35,
      "volume": 43456,
      "tradingAmount": 1824741,
      "transactionCount": 118
    },
    {
      "tradeDate": "2025-07-17",
      "open": 42.3,
      "high": 42.3,
      "low": 41.9,
      "close": 42.05,
      "change": 0.1,
      "volume": 216744,
      "tradingAmount": 9102732,
      "transactionCount": 184
    },
    {
      "tradeDate": "2025-07-18",
      "open": 42.5,
      "high": 42.8,
      "low": 42.05,
      "close": 42.35,
      "change": 0.3,
      "volume": 59878,
      "tradingAmount": 2533545,
      "transactionCount": 92
    },
    {
      "tradeDate": "2025-07-21",
      "open": 42.2,
      "high": 42.6,
      "low": 42.2,
      "close": 42.4,
      "change": 0.05,
      "volume": 41293,
      "tradingAmount": 1751532,
      "transactionCount": 75
    },
    {
      "tradeDate": "2025-07-22",
      "open": 42.45,
      "high": 42.75,
      "low": 42.25,
      "close": 42.35,
      "change": -0.05,
      "volume": 111359,
      "tradingAmount": 4723285,
      "transactionCount": 138
    },
    {
      "tradeDate": "2025-07-23",
      "open": 42.65,
      "high": 43.3,
      "low": 42.3,
      "close": 43.1,
      "change": 0.75,
      "volume": 81877,
      "tradingAmount": 3506772,
      "transactionCount": 107
    },
    {
      "tradeDate": "2025-07-24",
      "open": 43.1,
      "high": 43.35,
      "low": 42.85,
      "close": 42.9,
      "change": -0.2,
      "volume": 50690,
      "tradingAmount": 2179365,
      "transactionCount": 95
    },
    {
      "tradeDate": "2025-07-25",
      "open": 43.05,
      "high": 43.2,
      "low": 42.9,
      "close": 42.9,
      "change": 0,
      "volume": 27271,
      "tradingAmount": 1172807,
      "transactionCount": 88
    },
    {
      "tradeDate": "2025-07-28",
      "open": 42.3,
      "high": 42.85,
      "low": 42.3,
      "close": 42.75,
      "change": -0.15,
      "volume": 15766,
      "tradingAmount": 672933,
      "transactionCount": 102
    },
    {
      "tradeDate": "2025-07-29",
      "open": 42.75,
      "high": 42.8,
      "low": 42.5,
      "close": 42.75,
      "change": 0,
      "volume": 44255,
      "tradingAmount": 1886911,
      "transactionCount": 120
    },
    {
      "tradeDate": "2025-07-30",
      "open": 43,
      "high": 43,
      "low": 42.55,
      "close": 42.8,
      "change": 0.05,
      "volume": 48635,
      "tradingAmount": 2081217,
      "transactionCount": 73
    },
    {
      "tradeDate": "2025-07-31",
      "open": 42.8,
      "high": 42.8,
      "low": 42.6,
      "close": 42.8,
      "change": 0,
      "volume": 42442,
      "tradingAmount": 1812987,
      "transactionCount": 85
    },
    {
      "tradeDate": "2025-08-01",
      "open": 42.2,
      "high": 42.8,
      "low": 42.1,
      "close": 42.6,
      "change": -0.2,
      "volume": 41606,
      "tradingAmount": 1765692,
      "transactionCount": 80
    },
    {
      "tradeDate": "2025-08-04",
      "open": 42.85,
      "high": 43.15,
      "low": 42.45,
      "close": 42.85,
      "change": 0.25,
      "volume": 58070,
      "tradingAmount": 2493040,
      "transactionCount": 110
    },
    {
      "tradeDate": "2025-08-05",
      "open": 42.85,
      "high": 42.95,
      "low": 42.8,
      "close": 42.8,
      "change": -0.05,
      "volume": 48659,
      "tradingAmount": 2086001,
      "transactionCount": 96
    },
    {
      "tradeDate": "2025-08-06",
      "open": 42.8,
      "high": 43.3,
      "low": 42.75,
      "close": 43.1,
      "change": 0.3,
      "volume": 68351,
      "tradingAmount": 2942772,
      "transactionCount": 115
    },
    {
      "tradeDate": "2025-08-07",
      "open": 43.5,
      "high": 43.5,
      "low": 43,
      "close": 43.1,
      "change": 0,
      "volume": 68015,
      "tradingAmount": 2931604,
      "transactionCount": 252
    },
    {
      "tradeDate": "2025-08-08",
      "open": 43,
      "high": 43.15,
      "low": 42.55,
      "close": 43.15,
      "change": 0.05,
      "volume": 59677,
      "tradingAmount": 2565625,
      "transactionCount": 129
    },
    {
      "tradeDate": "2025-08-11",
      "open": 43.35,
      "high": 43.35,
      "low": 42.7,
      "close": 42.7,
      "change": -0.45,
      "volume": 31121,
      "tradingAmount": 1333218,
      "transactionCount": 160
    },
    {
      "tradeDate": "2025-08-12",
      "open": 42.75,
      "high": 42.85,
      "low": 42.6,
      "close": 42.6,
      "change": -0.1,
      "volume": 40856,
      "tradingAmount": 1745200,
      "transactionCount": 115
    },
    {
      "tradeDate": "2025-08-13",
      "open": 42.7,
      "high": 42.7,
      "low": 42.55,
      "close": 42.55,
      "change": -0.05,
      "volume": 52264,
      "tradingAmount": 2226983,
      "transactionCount": 147
    },
    {
      "tradeDate": "2025-08-14",
      "open": 42.55,
      "high": 42.9,
      "low": 42.55,
      "close": 42.9,
      "change": 0.35,
      "volume": 40219,
      "tradingAmount": 1717112,
      "transactionCount": 57
    },
    {
      "tradeDate": "2025-08-15",
      "open": 42.9,
      "high": 42.9,
      "low": 42.35,
      "close": 42.75,
      "change": -0.15,
      "volume": 103771,
      "tradingAmount": 4422144,
      "transactionCount": 193
    },
    {
      "tradeDate": "2025-08-18",
      "open": 42.7,
      "high": 43,
      "low": 42.7,
      "close": 43,
      "change": 0.25,
      "volume": 133244,
      "tradingAmount": 5713406,
      "transactionCount": 179
    },
    {
      "tradeDate": "2025-08-19",
      "open": 42.9,
      "high": 42.95,
      "low": 42.25,
      "close": 42.8,
      "change": -0.2,
      "volume": 109200,
      "tradingAmount": 4646771,
      "transactionCount": 204
    },
    {
      "tradeDate": "2025-08-20",
      "open": 42.55,
      "high": 42.8,
      "low": 42.25,
      "close": 42.3,
      "change": -0.5,
      "volume": 108560,
      "tradingAmount": 4603185,
      "transactionCount": 190
    },
    {
      "tradeDate": "2025-08-21",
      "open": 42.35,
      "high": 42.5,
      "low": 42.25,
      "close": 42.4,
      "change": 0.1,
      "volume": 58306,
      "tradingAmount": 2470955,
      "transactionCount": 175
    },
    {
      "tradeDate": "2025-08-22",
      "open": 42.3,
      "high": 42.5,
      "low": 42.2,
      "close": 42.3,
      "change": -0.1,
      "volume": 60373,
      "tradingAmount": 2557333,
      "transactionCount": 141
    },
    {
      "tradeDate": "2025-08-25",
      "open": 42.4,
      "high": 42.5,
      "low": 42.2,
      "close": 42.2,
      "change": -0.1,
      "volume": 98032,
      "tradingAmount": 4148857,
      "transactionCount": 147
    },
    {
      "tradeDate": "2025-08-26",
      "open": 42.1,
      "high": 42.2,
      "low": 41.75,
      "close": 41.9,
      "change": -0.3,
      "volume": 95450,
      "tradingAmount": 4003998,
      "transactionCount": 276
    },
    {
      "tradeDate": "2025-08-27",
      "open": 41.6,
      "high": 42.1,
      "low": 41.6,
      "close": 41.95,
      "change": 0.05,
      "volume": 35049,
      "tradingAmount": 1470550,
      "transactionCount": 165
    },
    {
      "tradeDate": "2025-08-28",
      "open": 42,
      "high": 42.35,
      "low": 42,
      "close": 42.05,
      "change": 0.1,
      "volume": 33699,
      "tradingAmount": 1421683,
      "transactionCount": 153
    },
    {
      "tradeDate": "2025-08-29",
      "open": 42.3,
      "high": 42.35,
      "low": 42.1,
      "close": 42.15,
      "change": 0.1,
      "volume": 35408,
      "tradingAmount": 1495854,
      "transactionCount": 64
    },
    {
      "tradeDate": "2025-09-01",
      "open": 42.45,
      "high": 42.45,
      "low": 41.85,
      "close": 42,
      "change": -0.15,
      "volume": 1002177,
      "tradingAmount": 42091660,
      "transactionCount": 78
    },
    {
      "tradeDate": "2025-09-02",
      "open": 42,
      "high": 42.15,
      "low": 41.9,
      "close": 42,
      "change": 0,
      "volume": 104255,
      "tradingAmount": 4377615,
      "transactionCount": 82
    },
    {
      "tradeDate": "2025-09-03",
      "open": 41.75,
      "high": 42.2,
      "low": 41.75,
      "close": 42,
      "change": 0,
      "volume": 28333,
      "tradingAmount": 1190731,
      "transactionCount": 97
    },
    {
      "tradeDate": "2025-09-04",
      "open": 42.1,
      "high": 42.6,
      "low": 42.1,
      "close": 42.6,
      "change": 0.6,
      "volume": 39154,
      "tradingAmount": 1662948,
      "transactionCount": 102
    },
    {
      "tradeDate": "2025-09-05",
      "open": 42.3,
      "high": 42.55,
      "low": 42.25,
      "close": 42.4,
      "change": -0.2,
      "volume": 31996,
      "tradingAmount": 1357113,
      "transactionCount": 154
    },
    {
      "tradeDate": "2025-09-08",
      "open": 42.35,
      "high": 42.95,
      "low": 42.2,
      "close": 42.55,
      "change": 0.15,
      "volume": 56609,
      "tradingAmount": 2416095,
      "transactionCount": 127
    },
    {
      "tradeDate": "2025-09-09",
      "open": 42.35,
      "high": 42.95,
      "low": 42.05,
      "close": 42.05,
      "change": -0.5,
      "volume": 116816,
      "tradingAmount": 4955761,
      "transactionCount": 122
    },
    {
      "tradeDate": "2025-09-10",
      "open": 41.95,
      "high": 42.55,
      "low": 41.9,
      "close": 42,
      "change": -0.05,
      "volume": 118874,
      "tradingAmount": 5014478,
      "transactionCount": 145
    },
    {
      "tradeDate": "2025-09-11",
      "open": 42,
      "high": 42.35,
      "low": 41.75,
      "close": 42.3,
      "change": 0.3,
      "volume": 100630,
      "tradingAmount": 4222914,
      "transactionCount": 192
    },
    {
      "tradeDate": "2025-09-12",
      "open": 42,
      "high": 42.3,
      "low": 41.9,
      "close": 42.1,
      "change": -0.2,
      "volume": 37956,
      "tradingAmount": 1601383,
      "transactionCount": 124
    },
    {
      "tradeDate": "2025-09-15",
      "open": 42.75,
      "high": 42.75,
      "low": 41.9,
      "close": 42.05,
      "change": -0.05,
      "volume": 22127,
      "tradingAmount": 932729,
      "transactionCount": 135
    },
    {
      "tradeDate": "2025-09-16",
      "open": 42.55,
      "high": 42.55,
      "low": 41.95,
      "close": 41.95,
      "change": -0.1,
      "volume": 56806,
      "tradingAmount": 2394703,
      "transactionCount": 126
    },
    {
      "tradeDate": "2025-09-17",
      "open": 41.95,
      "high": 42.2,
      "low": 41.85,
      "close": 41.85,
      "change": -0.1,
      "volume": 35584,
      "tradingAmount": 1494777,
      "transactionCount": 112
    },
    {
      "tradeDate": "2025-09-18",
      "open": 41.75,
      "high": 42.4,
      "low": 41.75,
      "close": 42,
      "change": 0.15,
      "volume": 470446,
      "tradingAmount": 19794462,
      "transactionCount": 120
    },
    {
      "tradeDate": "2025-09-19",
      "open": 42.05,
      "high": 42.2,
      "low": 41.75,
      "close": 42.2,
      "change": 0.2,
      "volume": 65245,
      "tradingAmount": 2739336,
      "transactionCount": 118
    },
    {
      "tradeDate": "2025-09-22",
      "open": 42.2,
      "high": 42.2,
      "low": 41.65,
      "close": 41.75,
      "change": -0.45,
      "volume": 188498,
      "tradingAmount": 7870974,
      "transactionCount": 272
    },
    {
      "tradeDate": "2025-09-23",
      "open": 41.75,
      "high": 42.3,
      "low": 41.7,
      "close": 42.15,
      "change": 0.4,
      "volume": 53844,
      "tradingAmount": 2255549,
      "transactionCount": 138
    },
    {
      "tradeDate": "2025-09-24",
      "open": 42,
      "high": 42.3,
      "low": 41.8,
      "close": 41.85,
      "change": -0.3,
      "volume": 62387,
      "tradingAmount": 2619194,
      "transactionCount": 121
    },
    {
      "tradeDate": "2025-09-25",
      "open": 42,
      "high": 42.5,
      "low": 41.85,
      "close": 42.3,
      "change": 0.45,
      "volume": 112884,
      "tradingAmount": 4764098,
      "transactionCount": 118
    },
    {
      "tradeDate": "2025-09-26",
      "open": 42.3,
      "high": 42.3,
      "low": 41.75,
      "close": 42,
      "change": -0.3,
      "volume": 77134,
      "tradingAmount": 3237745,
      "transactionCount": 189
    },
    {
      "tradeDate": "2025-09-30",
      "open": 42.6,
      "high": 42.6,
      "low": 41.9,
      "close": 42.15,
      "change": 0.15,
      "volume": 39200,
      "tradingAmount": 1658007,
      "transactionCount": 88
    },
    {
      "tradeDate": "2025-10-01",
      "open": 42,
      "high": 42.15,
      "low": 41.7,
      "close": 41.8,
      "change": -0.35,
      "volume": 47314,
      "tradingAmount": 1981520,
      "transactionCount": 202
    },
    {
      "tradeDate": "2025-10-02",
      "open": 41.8,
      "high": 41.9,
      "low": 41.55,
      "close": 41.7,
      "change": -0.1,
      "volume": 47940,
      "tradingAmount": 1998344,
      "transactionCount": 120
    },
    {
      "tradeDate": "2025-10-03",
      "open": 41.7,
      "high": 42.1,
      "low": 41.7,
      "close": 41.8,
      "change": 0.1,
      "volume": 37998,
      "tradingAmount": 1592529,
      "transactionCount": 90
    },
    {
      "tradeDate": "2025-10-07",
      "open": 41.8,
      "high": 42.1,
      "low": 41.6,
      "close": 42,
      "change": 0.2,
      "volume": 64099,
      "tradingAmount": 2685269,
      "transactionCount": 115
    },
    {
      "tradeDate": "2025-10-08",
      "open": 42.65,
      "high": 42.65,
      "low": 41.75,
      "close": 41.95,
      "change": -0.05,
      "volume": 50880,
      "tradingAmount": 2135684,
      "transactionCount": 72
    },
    {
      "tradeDate": "2025-10-09",
      "open": 41.9,
      "high": 42,
      "low": 41.65,
      "close": 41.8,
      "change": -0.15,
      "volume": 46812,
      "tradingAmount": 1957801,
      "transactionCount": 130
    },
    {
      "tradeDate": "2025-10-13",
      "open": 40.1,
      "high": 41.5,
      "low": 40.1,
      "close": 41.05,
      "change": -0.75,
      "volume": 96608,
      "tradingAmount": 3953060,
      "transactionCount": 309
    },
    {
      "tradeDate": "2025-10-14",
      "open": 41.15,
      "high": 41.75,
      "low": 41.1,
      "close": 41.3,
      "change": 0.25,
      "volume": 69677,
      "tradingAmount": 2881097,
      "transactionCount": 147
    },
    {
      "tradeDate": "2025-10-15",
      "open": 41.05,
      "high": 41.3,
      "low": 40.95,
      "close": 41.05,
      "change": -0.25,
      "volume": 53469,
      "tradingAmount": 2198754,
      "transactionCount": 219
    },
    {
      "tradeDate": "2025-10-16",
      "open": 41.05,
      "high": 41.8,
      "low": 41,
      "close": 41.7,
      "change": 0.65,
      "volume": 37726,
      "tradingAmount": 1559587,
      "transactionCount": 112
    },
    {
      "tradeDate": "2025-10-17",
      "open": 41.75,
      "high": 41.75,
      "low": 41.3,
      "close": 41.35,
      "change": -0.35,
      "volume": 44490,
      "tradingAmount": 1846402,
      "transactionCount": 99
    },
    {
      "tradeDate": "2025-10-20",
      "open": 41.4,
      "high": 41.5,
      "low": 41.4,
      "close": 41.5,
      "change": 0.15,
      "volume": 23608,
      "tradingAmount": 978424,
      "transactionCount": 109
    },
    {
      "tradeDate": "2025-10-21",
      "open": 41.5,
      "high": 41.5,
      "low": 41.2,
      "close": 41.2,
      "change": -0.3,
      "volume": 46620,
      "tradingAmount": 1926405,
      "transactionCount": 125
    },
    {
      "tradeDate": "2025-10-22",
      "open": 41.2,
      "high": 41.85,
      "low": 41.15,
      "close": 41.2,
      "change": 0,
      "volume": 37364,
      "tradingAmount": 1545896,
      "transactionCount": 77
    },
    {
      "tradeDate": "2025-10-23",
      "open": 42,
      "high": 42,
      "low": 41.3,
      "close": 41.45,
      "change": 0.25,
      "volume": 42236,
      "tradingAmount": 1758126,
      "transactionCount": 96
    },
    {
      "tradeDate": "2025-10-27",
      "open": 42.05,
      "high": 42.05,
      "low": 41.4,
      "close": 41.55,
      "change": 0.1,
      "volume": 42368,
      "tradingAmount": 1766870,
      "transactionCount": 100
    },
    {
      "tradeDate": "2025-10-28",
      "open": 41.55,
      "high": 41.85,
      "low": 41.2,
      "close": 41.65,
      "change": 0.1,
      "volume": 84128,
      "tradingAmount": 3480593,
      "transactionCount": 115
    },
    {
      "tradeDate": "2025-10-29",
      "open": 41.6,
      "high": 41.7,
      "low": 41.4,
      "close": 41.55,
      "change": -0.1,
      "volume": 65371,
      "tradingAmount": 2714452,
      "transactionCount": 101
    },
    {
      "tradeDate": "2025-10-30",
      "open": 41.55,
      "high": 41.6,
      "low": 41.4,
      "close": 41.4,
      "change": -0.15,
      "volume": 54472,
      "tradingAmount": 2257627,
      "transactionCount": 101
    },
    {
      "tradeDate": "2025-10-31",
      "open": 41.6,
      "high": 41.6,
      "low": 41.15,
      "close": 41.15,
      "change": -0.25,
      "volume": 42766,
      "tradingAmount": 1767488,
      "transactionCount": 160
    },
    {
      "tradeDate": "2025-11-03",
      "open": 41.1,
      "high": 41.2,
      "low": 40.75,
      "close": 40.85,
      "change": -0.3,
      "volume": 66397,
      "tradingAmount": 2719546,
      "transactionCount": 241
    },
    {
      "tradeDate": "2025-11-04",
      "open": 40.85,
      "high": 40.9,
      "low": 40.5,
      "close": 40.6,
      "change": -0.25,
      "volume": 45070,
      "tradingAmount": 1833414,
      "transactionCount": 146
    },
    {
      "tradeDate": "2025-11-05",
      "open": 40.6,
      "high": 40.6,
      "low": 40.1,
      "close": 40.2,
      "change": -0.4,
      "volume": 127014,
      "tradingAmount": 5109455,
      "transactionCount": 297
    },
    {
      "tradeDate": "2025-11-06",
      "open": 40.45,
      "high": 41,
      "low": 40.4,
      "close": 41,
      "change": 0.8,
      "volume": 57584,
      "tradingAmount": 2344343,
      "transactionCount": 184
    },
    {
      "tradeDate": "2025-11-07",
      "open": 41,
      "high": 41.5,
      "low": 41,
      "close": 41.25,
      "change": 0.25,
      "volume": 64814,
      "tradingAmount": 2671039,
      "transactionCount": 203
    },
    {
      "tradeDate": "2025-11-10",
      "open": 41.25,
      "high": 41.25,
      "low": 40,
      "close": 40.1,
      "change": -1.15,
      "volume": 210912,
      "tradingAmount": 8506643,
      "transactionCount": 329
    },
    {
      "tradeDate": "2025-11-11",
      "open": 40.2,
      "high": 40.6,
      "low": 40.15,
      "close": 40.5,
      "change": 0.4,
      "volume": 67446,
      "tradingAmount": 2718884,
      "transactionCount": 165
    },
    {
      "tradeDate": "2025-11-12",
      "open": 40.7,
      "high": 41,
      "low": 40.6,
      "close": 40.7,
      "change": 0.2,
      "volume": 46124,
      "tradingAmount": 1879677,
      "transactionCount": 150
    },
    {
      "tradeDate": "2025-11-13",
      "open": 40.8,
      "high": 41.3,
      "low": 40.8,
      "close": 41.1,
      "change": 0.4,
      "volume": 46612,
      "tradingAmount": 1912268,
      "transactionCount": 93
    },
    {
      "tradeDate": "2025-11-14",
      "open": 41.1,
      "high": 41.15,
      "low": 41,
      "close": 41,
      "change": -0.1,
      "volume": 18293,
      "tradingAmount": 751324,
      "transactionCount": 78
    },
    {
      "tradeDate": "2025-11-17",
      "open": 41.35,
      "high": 41.35,
      "low": 40.6,
      "close": 40.65,
      "change": -0.35,
      "volume": 44771,
      "tradingAmount": 1827737,
      "transactionCount": 121
    },
    {
      "tradeDate": "2025-11-18",
      "open": 40.5,
      "high": 40.85,
      "low": 40.3,
      "close": 40.3,
      "change": -0.35,
      "volume": 40973,
      "tradingAmount": 1657994,
      "transactionCount": 141
    },
    {
      "tradeDate": "2025-11-19",
      "open": 40.35,
      "high": 41.5,
      "low": 40.1,
      "close": 41.2,
      "change": 0.9,
      "volume": 153739,
      "tradingAmount": 6281061,
      "transactionCount": 220
    },
    {
      "tradeDate": "2025-11-20",
      "open": 41.2,
      "high": 41.2,
      "low": 40.55,
      "close": 40.65,
      "change": -0.55,
      "volume": 71306,
      "tradingAmount": 2908526,
      "transactionCount": 213
    },
    {
      "tradeDate": "2025-11-21",
      "open": 41.05,
      "high": 41.05,
      "low": 40.4,
      "close": 40.4,
      "change": -0.25,
      "volume": 57950,
      "tradingAmount": 2352112,
      "transactionCount": 207
    },
    {
      "tradeDate": "2025-11-24",
      "open": 40.5,
      "high": 40.75,
      "low": 40.4,
      "close": 40.6,
      "change": 0.2,
      "volume": 27554,
      "tradingAmount": 1116507,
      "transactionCount": 80
    },
    {
      "tradeDate": "2025-11-25",
      "open": 40.45,
      "high": 40.85,
      "low": 40.45,
      "close": 40.7,
      "change": 0.1,
      "volume": 29504,
      "tradingAmount": 1199250,
      "transactionCount": 65
    },
    {
      "tradeDate": "2025-11-26",
      "open": 40.65,
      "high": 41.05,
      "low": 40.65,
      "close": 41,
      "change": 0.3,
      "volume": 45809,
      "tradingAmount": 1874587,
      "transactionCount": 83
    },
    {
      "tradeDate": "2025-11-27",
      "open": 41.25,
      "high": 42.75,
      "low": 41.25,
      "close": 42,
      "change": 1,
      "volume": 224845,
      "tradingAmount": 9485416,
      "transactionCount": 237
    },
    {
      "tradeDate": "2025-11-28",
      "open": 41.95,
      "high": 42.4,
      "low": 41.9,
      "close": 42.35,
      "change": 0.35,
      "volume": 113221,
      "tradingAmount": 4771976,
      "transactionCount": 163
    },
    {
      "tradeDate": "2025-12-01",
      "open": 42.4,
      "high": 42.75,
      "low": 42.2,
      "close": 42.35,
      "change": 0,
      "volume": 154296,
      "tradingAmount": 6552199,
      "transactionCount": 192
    },
    {
      "tradeDate": "2025-12-02",
      "open": 42.35,
      "high": 42.65,
      "low": 42.35,
      "close": 42.55,
      "change": 0.2,
      "volume": 96965,
      "tradingAmount": 4122118,
      "transactionCount": 164
    },
    {
      "tradeDate": "2025-12-03",
      "open": 42.7,
      "high": 42.75,
      "low": 42.5,
      "close": 42.55,
      "change": 0,
      "volume": 41031,
      "tradingAmount": 1747189,
      "transactionCount": 84
    },
    {
      "tradeDate": "2025-12-04",
      "open": 42.7,
      "high": 42.7,
      "low": 42.4,
      "close": 42.55,
      "change": 0,
      "volume": 47865,
      "tradingAmount": 2036587,
      "transactionCount": 72
    },
    {
      "tradeDate": "2025-12-05",
      "open": 42.5,
      "high": 42.5,
      "low": 42,
      "close": 42.35,
      "change": -0.2,
      "volume": 74942,
      "tradingAmount": 3168520,
      "transactionCount": 96
    },
    {
      "tradeDate": "2025-12-08",
      "open": 42.3,
      "high": 42.3,
      "low": 41.95,
      "close": 41.95,
      "change": -0.4,
      "volume": 47417,
      "tradingAmount": 1994332,
      "transactionCount": 118
    },
    {
      "tradeDate": "2025-12-09",
      "open": 41.9,
      "high": 41.9,
      "low": 41.75,
      "close": 41.75,
      "change": -0.2,
      "volume": 29401,
      "tradingAmount": 1229944,
      "transactionCount": 78
    },
    {
      "tradeDate": "2025-12-10",
      "open": 41.8,
      "high": 42.25,
      "low": 41.8,
      "close": 42,
      "change": 0.25,
      "volume": 45404,
      "tradingAmount": 1905130,
      "transactionCount": 83
    },
    {
      "tradeDate": "2025-12-11",
      "open": 42,
      "high": 42.3,
      "low": 41.8,
      "close": 41.85,
      "change": -0.15,
      "volume": 68371,
      "tradingAmount": 2877842,
      "transactionCount": 105
    },
    {
      "tradeDate": "2025-12-12",
      "open": 42.25,
      "high": 42.45,
      "low": 42,
      "close": 42.05,
      "change": 0.2,
      "volume": 19174,
      "tradingAmount": 810771,
      "transactionCount": 43
    },
    {
      "tradeDate": "2025-12-15",
      "open": 42.5,
      "high": 42.5,
      "low": 41.95,
      "close": 42.15,
      "change": 0.1,
      "volume": 64056,
      "tradingAmount": 2707682,
      "transactionCount": 163
    },
    {
      "tradeDate": "2025-12-16",
      "open": 41.55,
      "high": 42.4,
      "low": 41.5,
      "close": 41.8,
      "change": -0.35,
      "volume": 73078,
      "tradingAmount": 3045851,
      "transactionCount": 110
    },
    {
      "tradeDate": "2025-12-17",
      "open": 41.85,
      "high": 41.85,
      "low": 41.35,
      "close": 41.5,
      "change": -0.3,
      "volume": 82628,
      "tradingAmount": 3436058,
      "transactionCount": 156
    },
    {
      "tradeDate": "2025-12-18",
      "open": 41.55,
      "high": 41.95,
      "low": 41.5,
      "close": 41.85,
      "change": 0.35,
      "volume": 32484,
      "tradingAmount": 1359520,
      "transactionCount": 47
    },
    {
      "tradeDate": "2025-12-19",
      "open": 41.85,
      "high": 42.2,
      "low": 41.75,
      "close": 41.9,
      "change": 0.05,
      "volume": 62681,
      "tradingAmount": 2624607,
      "transactionCount": 92
    },
    {
      "tradeDate": "2025-12-22",
      "open": 41.9,
      "high": 42,
      "low": 41.9,
      "close": 42,
      "change": 0.1,
      "volume": 16056,
      "tradingAmount": 673406,
      "transactionCount": 81
    },
    {
      "tradeDate": "2025-12-23",
      "open": 41.7,
      "high": 42,
      "low": 41.6,
      "close": 41.6,
      "change": -0.4,
      "volume": 31732,
      "tradingAmount": 1324921,
      "transactionCount": 86
    },
    {
      "tradeDate": "2025-12-24",
      "open": 41.8,
      "high": 42,
      "low": 41.3,
      "close": 41.4,
      "change": -0.2,
      "volume": 65968,
      "tradingAmount": 2738169,
      "transactionCount": 123
    },
    {
      "tradeDate": "2025-12-26",
      "open": 41.95,
      "high": 41.95,
      "low": 41.4,
      "close": 41.65,
      "change": 0.25,
      "volume": 51049,
      "tradingAmount": 2126576,
      "transactionCount": 122
    },
    {
      "tradeDate": "2025-12-29",
      "open": 41.75,
      "high": 42,
      "low": 41.6,
      "close": 41.95,
      "change": 0.3,
      "volume": 153349,
      "tradingAmount": 6408300,
      "transactionCount": 128
    },
    {
      "tradeDate": "2025-12-30",
      "open": 41.9,
      "high": 42,
      "low": 41.8,
      "close": 41.95,
      "change": 0,
      "volume": 16599,
      "tradingAmount": 696226,
      "transactionCount": 75
    },
    {
      "tradeDate": "2025-12-31",
      "open": 41.9,
      "high": 42,
      "low": 41.6,
      "close": 41.9,
      "change": -0.05,
      "volume": 67874,
      "tradingAmount": 2836758,
      "transactionCount": 103
    },
    {
      "tradeDate": "2026-01-02",
      "open": 42.05,
      "high": 42.2,
      "low": 41.95,
      "close": 41.95,
      "change": 0.05,
      "volume": 52108,
      "tradingAmount": 2189121,
      "transactionCount": 95
    },
    {
      "tradeDate": "2026-01-05",
      "open": 42.35,
      "high": 45,
      "low": 42.35,
      "close": 43.2,
      "change": 1.25,
      "volume": 640334,
      "tradingAmount": 27810586,
      "transactionCount": 550
    },
    {
      "tradeDate": "2026-01-06",
      "open": 43.25,
      "high": 43.8,
      "low": 42.55,
      "close": 42.8,
      "change": -0.4,
      "volume": 252876,
      "tradingAmount": 10923913,
      "transactionCount": 565
    },
    {
      "tradeDate": "2026-01-07",
      "open": 42.8,
      "high": 43.1,
      "low": 42.35,
      "close": 42.8,
      "change": 0,
      "volume": 511083,
      "tradingAmount": 21791393,
      "transactionCount": 458
    },
    {
      "tradeDate": "2026-01-08",
      "open": 43.2,
      "high": 43.5,
      "low": 42.5,
      "close": 42.5,
      "change": -0.3,
      "volume": 210802,
      "tradingAmount": 9082652,
      "transactionCount": 256
    },
    {
      "tradeDate": "2026-01-09",
      "open": 42.55,
      "high": 42.6,
      "low": 42.35,
      "close": 42.55,
      "change": 0.05,
      "volume": 97264,
      "tradingAmount": 4130051,
      "transactionCount": 201
    },
    {
      "tradeDate": "2026-01-12",
      "open": 42.9,
      "high": 43.1,
      "low": 42.5,
      "close": 42.6,
      "change": 0.05,
      "volume": 269497,
      "tradingAmount": 11512310,
      "transactionCount": 202
    },
    {
      "tradeDate": "2026-01-13",
      "open": 42.65,
      "high": 43.15,
      "low": 42.45,
      "close": 42.6,
      "change": 0,
      "volume": 83847,
      "tradingAmount": 3570062,
      "transactionCount": 198
    },
    {
      "tradeDate": "2026-01-14",
      "open": 42.6,
      "high": 42.8,
      "low": 42.4,
      "close": 42.55,
      "change": -0.05,
      "volume": 260030,
      "tradingAmount": 11076943,
      "transactionCount": 194
    },
    {
      "tradeDate": "2026-01-15",
      "open": 42.6,
      "high": 42.95,
      "low": 42.5,
      "close": 42.75,
      "change": 0.2,
      "volume": 402159,
      "tradingAmount": 17131159,
      "transactionCount": 211
    },
    {
      "tradeDate": "2026-01-16",
      "open": 42.75,
      "high": 42.8,
      "low": 42.3,
      "close": 42.65,
      "change": -0.1,
      "volume": 124635,
      "tradingAmount": 5298551,
      "transactionCount": 191
    },
    {
      "tradeDate": "2026-01-19",
      "open": 42.5,
      "high": 42.7,
      "low": 42.45,
      "close": 42.45,
      "change": -0.2,
      "volume": 163484,
      "tradingAmount": 6950970,
      "transactionCount": 291
    },
    {
      "tradeDate": "2026-01-20",
      "open": 42.6,
      "high": 42.8,
      "low": 42.35,
      "close": 42.35,
      "change": -0.1,
      "volume": 118048,
      "tradingAmount": 5020773,
      "transactionCount": 174
    },
    {
      "tradeDate": "2026-01-21",
      "open": 42.2,
      "high": 42.35,
      "low": 41.45,
      "close": 41.65,
      "change": -0.7,
      "volume": 333829,
      "tradingAmount": 13907383,
      "transactionCount": 520
    },
    {
      "tradeDate": "2026-01-22",
      "open": 41.9,
      "high": 42,
      "low": 41.65,
      "close": 41.65,
      "change": 0,
      "volume": 146518,
      "tradingAmount": 6126478,
      "transactionCount": 182
    },
    {
      "tradeDate": "2026-01-23",
      "open": 41.65,
      "high": 41.7,
      "low": 41.45,
      "close": 41.7,
      "change": 0.05,
      "volume": 209073,
      "tradingAmount": 8683843,
      "transactionCount": 232
    },
    {
      "tradeDate": "2026-01-26",
      "open": 41.8,
      "high": 41.9,
      "low": 41.65,
      "close": 41.85,
      "change": 0.15,
      "volume": 137205,
      "tradingAmount": 5724924,
      "transactionCount": 168
    },
    {
      "tradeDate": "2026-01-27",
      "open": 41.9,
      "high": 42.05,
      "low": 41.45,
      "close": 41.8,
      "change": -0.05,
      "volume": 225676,
      "tradingAmount": 9387495,
      "transactionCount": 314
    },
    {
      "tradeDate": "2026-01-28",
      "open": 41.8,
      "high": 41.85,
      "low": 41.6,
      "close": 41.8,
      "change": 0,
      "volume": 72853,
      "tradingAmount": 3038745,
      "transactionCount": 127
    },
    {
      "tradeDate": "2026-01-29",
      "open": 41.8,
      "high": 43.4,
      "low": 41.75,
      "close": 43,
      "change": 1.2,
      "volume": 601294,
      "tradingAmount": 25764659,
      "transactionCount": 568
    },
    {
      "tradeDate": "2026-01-30",
      "open": 42.85,
      "high": 43.95,
      "low": 42.6,
      "close": 42.95,
      "change": -0.05,
      "volume": 571028,
      "tradingAmount": 24685876,
      "transactionCount": 822
    },
    {
      "tradeDate": "2026-02-02",
      "open": 43.35,
      "high": 43.35,
      "low": 42.05,
      "close": 42.05,
      "change": -0.9,
      "volume": 201462,
      "tradingAmount": 8549200,
      "transactionCount": 452
    },
    {
      "tradeDate": "2026-02-03",
      "open": 43.2,
      "high": 43.2,
      "low": 41.8,
      "close": 41.8,
      "change": -0.25,
      "volume": 184103,
      "tradingAmount": 7758250,
      "transactionCount": 408
    },
    {
      "tradeDate": "2026-02-04",
      "open": 42.1,
      "high": 42.25,
      "low": 41.8,
      "close": 41.8,
      "change": 0,
      "volume": 53529,
      "tradingAmount": 2248811,
      "transactionCount": 109
    },
    {
      "tradeDate": "2026-02-05",
      "open": 41.8,
      "high": 42,
      "low": 41.7,
      "close": 41.7,
      "change": -0.1,
      "volume": 101940,
      "tradingAmount": 4265475,
      "transactionCount": 170
    },
    {
      "tradeDate": "2026-02-06",
      "open": 41.55,
      "high": 41.65,
      "low": 41.1,
      "close": 41.2,
      "change": -0.5,
      "volume": 92334,
      "tradingAmount": 3821112,
      "transactionCount": 213
    },
    {
      "tradeDate": "2026-02-09",
      "open": 41.5,
      "high": 41.5,
      "low": 41.1,
      "close": 41.35,
      "change": 0.15,
      "volume": 80821,
      "tradingAmount": 3340883,
      "transactionCount": 124
    },
    {
      "tradeDate": "2026-02-10",
      "open": 41.35,
      "high": 41.5,
      "low": 41,
      "close": 41.4,
      "change": 0.05,
      "volume": 97648,
      "tradingAmount": 4029555,
      "transactionCount": 133
    },
    {
      "tradeDate": "2026-02-11",
      "open": 41.8,
      "high": 42,
      "low": 41.3,
      "close": 41.8,
      "change": 0.4,
      "volume": 123910,
      "tradingAmount": 5166453,
      "transactionCount": 157
    },
    {
      "tradeDate": "2026-02-23",
      "open": 42.2,
      "high": 42.45,
      "low": 42,
      "close": 42.2,
      "change": 0.4,
      "volume": 207684,
      "tradingAmount": 8764997,
      "transactionCount": 250
    },
    {
      "tradeDate": "2026-02-24",
      "open": 42.1,
      "high": 42.6,
      "low": 42.1,
      "close": 42.35,
      "change": 0.15,
      "volume": 82009,
      "tradingAmount": 3470709,
      "transactionCount": 338
    },
    {
      "tradeDate": "2026-02-25",
      "open": 42.6,
      "high": 43.45,
      "low": 42.6,
      "close": 43.05,
      "change": 0.7,
      "volume": 464682,
      "tradingAmount": 20036329,
      "transactionCount": 669
    },
    {
      "tradeDate": "2026-02-26",
      "open": 43.05,
      "high": 43.45,
      "low": 42.95,
      "close": 43.45,
      "change": 0.4,
      "volume": 201500,
      "tradingAmount": 8715518,
      "transactionCount": 736
    },
    {
      "tradeDate": "2026-03-02",
      "open": 43.5,
      "high": 43.6,
      "low": 42.9,
      "close": 43.15,
      "change": -0.3,
      "volume": 151481,
      "tradingAmount": 6534324,
      "transactionCount": 894
    },
    {
      "tradeDate": "2026-03-03",
      "open": 43,
      "high": 43.15,
      "low": 42.4,
      "close": 42.9,
      "change": -0.25,
      "volume": 183200,
      "tradingAmount": 7827379,
      "transactionCount": 523
    },
    {
      "tradeDate": "2026-03-04",
      "open": 42.55,
      "high": 42.9,
      "low": 41.8,
      "close": 41.9,
      "change": -1,
      "volume": 210170,
      "tradingAmount": 8862702,
      "transactionCount": 499
    },
    {
      "tradeDate": "2026-03-05",
      "open": 41.65,
      "high": 42.4,
      "low": 41.65,
      "close": 42.3,
      "change": 0.4,
      "volume": 142103,
      "tradingAmount": 5972795,
      "transactionCount": 263
    },
    {
      "tradeDate": "2026-03-06",
      "open": 42.3,
      "high": 43,
      "low": 42.15,
      "close": 42.9,
      "change": 0.6,
      "volume": 105804,
      "tradingAmount": 4520015,
      "transactionCount": 251
    },
    {
      "tradeDate": "2026-03-09",
      "open": 43.35,
      "high": 44,
      "low": 42.9,
      "close": 43.8,
      "change": 0.9,
      "volume": 625185,
      "tradingAmount": 27143694,
      "transactionCount": 717
    },
    {
      "tradeDate": "2026-03-10",
      "open": 44.75,
      "high": 44.75,
      "low": 43.75,
      "close": 44.25,
      "change": 0.45,
      "volume": 292011,
      "tradingAmount": 12859443,
      "transactionCount": 437
    },
    {
      "tradeDate": "2026-03-11",
      "open": 44.25,
      "high": 44.5,
      "low": 44.15,
      "close": 44.35,
      "change": 0.1,
      "volume": 270883,
      "tradingAmount": 12008777,
      "transactionCount": 404
    },
    {
      "tradeDate": "2026-03-12",
      "open": 44.3,
      "high": 44.35,
      "low": 43.5,
      "close": 43.65,
      "change": -0.7,
      "volume": 293435,
      "tradingAmount": 12871947,
      "transactionCount": 512
    },
    {
      "tradeDate": "2026-03-13",
      "open": 43.3,
      "high": 44.1,
      "low": 43.3,
      "close": 43.9,
      "change": 0.25,
      "volume": 131405,
      "tradingAmount": 5744572,
      "transactionCount": 230
    },
    {
      "tradeDate": "2026-03-16",
      "open": 44,
      "high": 44.1,
      "low": 43.8,
      "close": 44,
      "change": 0.1,
      "volume": 203687,
      "tradingAmount": 8964376,
      "transactionCount": 290
    },
    {
      "tradeDate": "2026-03-17",
      "open": 44.05,
      "high": 44.1,
      "low": 43.8,
      "close": 44.1,
      "change": 0.1,
      "volume": 114484,
      "tradingAmount": 5034598,
      "transactionCount": 201
    },
    {
      "tradeDate": "2026-03-18",
      "open": 44.25,
      "high": 44.7,
      "low": 44.2,
      "close": 44.35,
      "change": 0.25,
      "volume": 199964,
      "tradingAmount": 8885495,
      "transactionCount": 239
    },
    {
      "tradeDate": "2026-03-19",
      "open": 44,
      "high": 44.15,
      "low": 43.5,
      "close": 43.75,
      "change": -0.6,
      "volume": 227475,
      "tradingAmount": 9963180,
      "transactionCount": 343
    },
    {
      "tradeDate": "2026-03-20",
      "open": 43.6,
      "high": 45.5,
      "low": 43.6,
      "close": 44.45,
      "change": 0.7,
      "volume": 592468,
      "tradingAmount": 26700799,
      "transactionCount": 619
    },
    {
      "tradeDate": "2026-03-23",
      "open": 47,
      "high": 47,
      "low": 44,
      "close": 44,
      "change": -0.45,
      "volume": 774482,
      "tradingAmount": 34826115,
      "transactionCount": 767
    },
    {
      "tradeDate": "2026-03-24",
      "open": 44.15,
      "high": 45.35,
      "low": 44.1,
      "close": 45,
      "change": 1,
      "volume": 267802,
      "tradingAmount": 11980017,
      "transactionCount": 381
    },
    {
      "tradeDate": "2026-03-25",
      "open": 45.9,
      "high": 45.9,
      "low": 45,
      "close": 45.15,
      "change": 0.15,
      "volume": 267381,
      "tradingAmount": 12077288,
      "transactionCount": 401
    },
    {
      "tradeDate": "2026-03-26",
      "open": 45.65,
      "high": 45.65,
      "low": 44.85,
      "close": 45.05,
      "change": -0.1,
      "volume": 150565,
      "tradingAmount": 6796621,
      "transactionCount": 319
    },
    {
      "tradeDate": "2026-03-27",
      "open": 45.05,
      "high": 45.05,
      "low": 44.55,
      "close": 44.85,
      "change": -0.2,
      "volume": 98737,
      "tradingAmount": 4425426,
      "transactionCount": 315
    },
    {
      "tradeDate": "2026-03-30",
      "open": 44.15,
      "high": 45.55,
      "low": 44.15,
      "close": 44.45,
      "change": -0.4,
      "volume": 118852,
      "tradingAmount": 5296796,
      "transactionCount": 549
    },
    {
      "tradeDate": "2026-03-31",
      "open": 44.1,
      "high": 44.45,
      "low": 43.85,
      "close": 43.85,
      "change": -0.6,
      "volume": 128053,
      "tradingAmount": 5647197,
      "transactionCount": 192
    },
    {
      "tradeDate": "2026-04-01",
      "open": 44.45,
      "high": 44.5,
      "low": 44,
      "close": 44.05,
      "change": 0.2,
      "volume": 66271,
      "tradingAmount": 2924312,
      "transactionCount": 183
    },
    {
      "tradeDate": "2026-04-02",
      "open": 44.1,
      "high": 44.1,
      "low": 43.5,
      "close": 43.7,
      "change": -0.35,
      "volume": 74733,
      "tradingAmount": 3265629,
      "transactionCount": 122
    },
    {
      "tradeDate": "2026-04-07",
      "open": 43.7,
      "high": 44.1,
      "low": 43.5,
      "close": 43.55,
      "change": -0.15,
      "volume": 57498,
      "tradingAmount": 2512471,
      "transactionCount": 111
    },
    {
      "tradeDate": "2026-04-08",
      "open": 44,
      "high": 44.25,
      "low": 43.8,
      "close": 44.1,
      "change": 0.55,
      "volume": 104033,
      "tradingAmount": 4580330,
      "transactionCount": 143
    },
    {
      "tradeDate": "2026-04-09",
      "open": 44.1,
      "high": 44.4,
      "low": 43.8,
      "close": 44.3,
      "change": 0.2,
      "volume": 78842,
      "tradingAmount": 3481543,
      "transactionCount": 150
    },
    {
      "tradeDate": "2026-04-10",
      "open": 44.55,
      "high": 44.8,
      "low": 44.2,
      "close": 44.5,
      "change": 0.2,
      "volume": 89391,
      "tradingAmount": 3980095,
      "transactionCount": 156
    },
    {
      "tradeDate": "2026-04-13",
      "open": 44.5,
      "high": 44.5,
      "low": 43.85,
      "close": 44.2,
      "change": -0.3,
      "volume": 115234,
      "tradingAmount": 5081767,
      "transactionCount": 246
    },
    {
      "tradeDate": "2026-04-14",
      "open": 44.2,
      "high": 44.75,
      "low": 43.8,
      "close": 44,
      "change": -0.2,
      "volume": 125996,
      "tradingAmount": 5538581,
      "transactionCount": 226
    },
    {
      "tradeDate": "2026-04-15",
      "open": 44.15,
      "high": 44.25,
      "low": 43.7,
      "close": 43.75,
      "change": -0.25,
      "volume": 170002,
      "tradingAmount": 7454796,
      "transactionCount": 214
    },
    {
      "tradeDate": "2026-04-16",
      "open": 44.3,
      "high": 44.5,
      "low": 43.8,
      "close": 44.1,
      "change": 0.35,
      "volume": 136453,
      "tradingAmount": 6013320,
      "transactionCount": 185
    },
    {
      "tradeDate": "2026-04-17",
      "open": 44.05,
      "high": 44.2,
      "low": 43.75,
      "close": 44.05,
      "change": -0.05,
      "volume": 120780,
      "tradingAmount": 5305060,
      "transactionCount": 201
    },
    {
      "tradeDate": "2026-04-20",
      "open": 44.2,
      "high": 44.2,
      "low": 43.6,
      "close": 44.1,
      "change": 0.05,
      "volume": 125552,
      "tradingAmount": 5513842,
      "transactionCount": 215
    },
    {
      "tradeDate": "2026-04-21",
      "open": 44.1,
      "high": 44.1,
      "low": 43.8,
      "close": 44,
      "change": -0.1,
      "volume": 120082,
      "tradingAmount": 5270934,
      "transactionCount": 182
    },
    {
      "tradeDate": "2026-04-22",
      "open": 43.7,
      "high": 43.9,
      "low": 43.6,
      "close": 43.75,
      "change": -0.25,
      "volume": 125959,
      "tradingAmount": 5508681,
      "transactionCount": 158
    },
    {
      "tradeDate": "2026-04-23",
      "open": 43.7,
      "high": 43.7,
      "low": 42.7,
      "close": 42.9,
      "change": -0.85,
      "volume": 311934,
      "tradingAmount": 13444863,
      "transactionCount": 420
    },
    {
      "tradeDate": "2026-04-24",
      "open": 42.9,
      "high": 42.9,
      "low": 42.2,
      "close": 42.4,
      "change": -0.5,
      "volume": 180653,
      "tradingAmount": 7673221,
      "transactionCount": 340
    },
    {
      "tradeDate": "2026-04-27",
      "open": 42.45,
      "high": 42.7,
      "low": 42.2,
      "close": 42.55,
      "change": 0.15,
      "volume": 148336,
      "tradingAmount": 6289626,
      "transactionCount": 195
    },
    {
      "tradeDate": "2026-04-28",
      "open": 42.55,
      "high": 43.2,
      "low": 42.55,
      "close": 42.9,
      "change": 0.35,
      "volume": 49254,
      "tradingAmount": 2110558,
      "transactionCount": 87
    },
    {
      "tradeDate": "2026-04-29",
      "open": 43.15,
      "high": 43.15,
      "low": 42.6,
      "close": 43.05,
      "change": 0.15,
      "volume": 81470,
      "tradingAmount": 3488645,
      "transactionCount": 140
    },
    {
      "tradeDate": "2026-04-30",
      "open": 43,
      "high": 43,
      "low": 42.6,
      "close": 42.75,
      "change": -0.3,
      "volume": 54165,
      "tradingAmount": 2317877,
      "transactionCount": 136
    },
    {
      "tradeDate": "2026-05-04",
      "open": 42.75,
      "high": 42.75,
      "low": 42.5,
      "close": 42.7,
      "change": -0.05,
      "volume": 132526,
      "tradingAmount": 5649075,
      "transactionCount": 198
    },
    {
      "tradeDate": "2026-05-05",
      "open": 42.7,
      "high": 42.8,
      "low": 42.5,
      "close": 42.5,
      "change": -0.2,
      "volume": 70085,
      "tradingAmount": 2986932,
      "transactionCount": 125
    },
    {
      "tradeDate": "2026-05-06",
      "open": 43.2,
      "high": 43.2,
      "low": 42.6,
      "close": 43,
      "change": 0.5,
      "volume": 97961,
      "tradingAmount": 4205909,
      "transactionCount": 117
    },
    {
      "tradeDate": "2026-05-07",
      "open": 42.6,
      "high": 43.2,
      "low": 42.6,
      "close": 42.95,
      "change": -0.05,
      "volume": 112141,
      "tradingAmount": 4819302,
      "transactionCount": 186
    },
    {
      "tradeDate": "2026-05-08",
      "open": 42.9,
      "high": 43.2,
      "low": 42.65,
      "close": 42.8,
      "change": -0.15,
      "volume": 124237,
      "tradingAmount": 5336510,
      "transactionCount": 177
    },
    {
      "tradeDate": "2026-05-11",
      "open": 42.8,
      "high": 43.1,
      "low": 42.8,
      "close": 42.95,
      "change": 0.15,
      "volume": 83250,
      "tradingAmount": 3577859,
      "transactionCount": 144
    },
    {
      "tradeDate": "2026-05-12",
      "open": 42.95,
      "high": 43.4,
      "low": 42.6,
      "close": 42.6,
      "change": -0.35,
      "volume": 105689,
      "tradingAmount": 4512899,
      "transactionCount": 169
    },
    {
      "tradeDate": "2026-05-13",
      "open": 42.6,
      "high": 42.75,
      "low": 42.4,
      "close": 42.65,
      "change": 0.05,
      "volume": 85299,
      "tradingAmount": 3631061,
      "transactionCount": 102
    },
    {
      "tradeDate": "2026-05-14",
      "open": 42.4,
      "high": 42.8,
      "low": 42.4,
      "close": 42.5,
      "change": -0.15,
      "volume": 107776,
      "tradingAmount": 4593178,
      "transactionCount": 152
    },
    {
      "tradeDate": "2026-05-15",
      "open": 42.55,
      "high": 42.7,
      "low": 42.05,
      "close": 42.05,
      "change": -0.45,
      "volume": 173926,
      "tradingAmount": 7367307,
      "transactionCount": 215
    },
    {
      "tradeDate": "2026-05-18",
      "open": 41.8,
      "high": 42,
      "low": 41.7,
      "close": 41.8,
      "change": -0.25,
      "volume": 87380,
      "tradingAmount": 3658549,
      "transactionCount": 169
    },
    {
      "tradeDate": "2026-05-19",
      "open": 41.65,
      "high": 42,
      "low": 41.65,
      "close": 41.85,
      "change": 0.05,
      "volume": 62727,
      "tradingAmount": 2624875,
      "transactionCount": 100
    },
    {
      "tradeDate": "2026-05-20",
      "open": 41.8,
      "high": 42,
      "low": 41.6,
      "close": 41.95,
      "change": 0.1,
      "volume": 81269,
      "tradingAmount": 3398939,
      "transactionCount": 156
    },
    {
      "tradeDate": "2026-05-21",
      "open": 41.95,
      "high": 42.3,
      "low": 41.95,
      "close": 42.15,
      "change": 0.2,
      "volume": 75740,
      "tradingAmount": 3191320,
      "transactionCount": 106
    },
    {
      "tradeDate": "2026-05-22",
      "open": 42.05,
      "high": 42.15,
      "low": 41.9,
      "close": 41.9,
      "change": -0.25,
      "volume": 99507,
      "tradingAmount": 4178002,
      "transactionCount": 133
    },
    {
      "tradeDate": "2026-05-25",
      "open": 42,
      "high": 43,
      "low": 41.7,
      "close": 42.8,
      "change": 0.9,
      "volume": 266112,
      "tradingAmount": 11293910,
      "transactionCount": 297
    },
    {
      "tradeDate": "2026-05-26",
      "open": 42.9,
      "high": 43.15,
      "low": 42.45,
      "close": 42.5,
      "change": -0.3,
      "volume": 170031,
      "tradingAmount": 7268849,
      "transactionCount": 227
    },
    {
      "tradeDate": "2026-05-27",
      "open": 42.5,
      "high": 42.75,
      "low": 42.3,
      "close": 42.4,
      "change": -0.1,
      "volume": 125283,
      "tradingAmount": 5318509,
      "transactionCount": 163
    },
    {
      "tradeDate": "2026-05-28",
      "open": 42.4,
      "high": 42.8,
      "low": 42.4,
      "close": 42.4,
      "change": 0,
      "volume": 109273,
      "tradingAmount": 4651323,
      "transactionCount": 130
    },
    {
      "tradeDate": "2026-05-29",
      "open": 42.45,
      "high": 42.75,
      "low": 42.2,
      "close": 42.45,
      "change": 0.05,
      "volume": 99774,
      "tradingAmount": 4231330,
      "transactionCount": 141
    },
    {
      "tradeDate": "2026-06-01",
      "open": 42.5,
      "high": 42.7,
      "low": 42.05,
      "close": 42.55,
      "change": 0.1,
      "volume": 133014,
      "tradingAmount": 5649088,
      "transactionCount": 166
    },
    {
      "tradeDate": "2026-06-02",
      "open": 42.7,
      "high": 42.7,
      "low": 42.35,
      "close": 42.6,
      "change": 0.05,
      "volume": 169845,
      "tradingAmount": 7219903,
      "transactionCount": 180
    },
    {
      "tradeDate": "2026-06-03",
      "open": 42.6,
      "high": 43.25,
      "low": 42.25,
      "close": 43.2,
      "change": 0.6,
      "volume": 300357,
      "tradingAmount": 12888406,
      "transactionCount": 244
    },
    {
      "tradeDate": "2026-06-04",
      "open": 43.25,
      "high": 43.5,
      "low": 42.95,
      "close": 43.3,
      "change": 0.1,
      "volume": 204443,
      "tradingAmount": 8836798,
      "transactionCount": 198
    },
    {
      "tradeDate": "2026-06-05",
      "open": 43.8,
      "high": 43.8,
      "low": 43.1,
      "close": 43.35,
      "change": 0.05,
      "volume": 107045,
      "tradingAmount": 4629067,
      "transactionCount": 143
    },
    {
      "tradeDate": "2026-06-08",
      "open": 41.8,
      "high": 42.85,
      "low": 41.8,
      "close": 42.35,
      "change": -1,
      "volume": 155564,
      "tradingAmount": 6588194,
      "transactionCount": 194
    },
    {
      "tradeDate": "2026-06-09",
      "open": 42.1,
      "high": 42.85,
      "low": 42.1,
      "close": 42.75,
      "change": 0.4,
      "volume": 124330,
      "tradingAmount": 5289041,
      "transactionCount": 180
    },
    {
      "tradeDate": "2026-06-10",
      "open": 42.3,
      "high": 42.7,
      "low": 42.15,
      "close": 42.6,
      "change": -0.15,
      "volume": 155517,
      "tradingAmount": 6596611,
      "transactionCount": 228
    },
    {
      "tradeDate": "2026-06-11",
      "open": 42.6,
      "high": 42.8,
      "low": 42.15,
      "close": 42.8,
      "change": 0.2,
      "volume": 104754,
      "tradingAmount": 4447976,
      "transactionCount": 130
    },
    {
      "tradeDate": "2026-06-12",
      "open": 42.8,
      "high": 43.1,
      "low": 42.65,
      "close": 43,
      "change": 0.2,
      "volume": 94925,
      "tradingAmount": 4075866,
      "transactionCount": 128
    },
    {
      "tradeDate": "2026-06-15",
      "open": 43.25,
      "high": 43.25,
      "low": 43,
      "close": 43.15,
      "change": 0.15,
      "volume": 125381,
      "tradingAmount": 5409957,
      "transactionCount": 156
    },
    {
      "tradeDate": "2026-06-16",
      "open": 43.15,
      "high": 43.25,
      "low": 43,
      "close": 43.15,
      "change": 0,
      "volume": 137772,
      "tradingAmount": 5944925,
      "transactionCount": 185
    },
    {
      "tradeDate": "2026-06-17",
      "open": 43.25,
      "high": 43.5,
      "low": 43.1,
      "close": 43.2,
      "change": 0.05,
      "volume": 116013,
      "tradingAmount": 5022664,
      "transactionCount": 150
    },
    {
      "tradeDate": "2026-06-18",
      "open": 43.25,
      "high": 43.6,
      "low": 42.9,
      "close": 42.9,
      "change": -0.3,
      "volume": 206750,
      "tradingAmount": 8942942,
      "transactionCount": 269
    },
    {
      "tradeDate": "2026-06-22",
      "open": 43.05,
      "high": 43.05,
      "low": 42.8,
      "close": 42.95,
      "change": 0.05,
      "volume": 98568,
      "tradingAmount": 4230657,
      "transactionCount": 179
    },
    {
      "tradeDate": "2026-06-23",
      "open": 43,
      "high": 43.1,
      "low": 42.7,
      "close": 43.05,
      "change": 0.1,
      "volume": 157592,
      "tradingAmount": 6762314,
      "transactionCount": 243
    },
    {
      "tradeDate": "2026-06-24",
      "open": 43,
      "high": 43.7,
      "low": 43,
      "close": 43.7,
      "change": 0.65,
      "volume": 169366,
      "tradingAmount": 7373418,
      "transactionCount": 225
    },
    {
      "tradeDate": "2026-06-25",
      "open": 44,
      "high": 44.3,
      "low": 43.6,
      "close": 43.95,
      "change": 0.25,
      "volume": 311039,
      "tradingAmount": 13668603,
      "transactionCount": 340
    },
    {
      "tradeDate": "2026-06-26",
      "open": 43.95,
      "high": 44.35,
      "low": 43.7,
      "close": 43.75,
      "change": -0.2,
      "volume": 332490,
      "tradingAmount": 14645575,
      "transactionCount": 460
    },
    {
      "tradeDate": "2026-06-29",
      "open": 43.15,
      "high": 44.25,
      "low": 43.15,
      "close": 43.95,
      "change": 0.2,
      "volume": 186964,
      "tradingAmount": 8223132,
      "transactionCount": 224
    },
    {
      "tradeDate": "2026-06-30",
      "open": 44,
      "high": 44,
      "low": 43.5,
      "close": 43.6,
      "change": -0.35,
      "volume": 233194,
      "tradingAmount": 10183831,
      "transactionCount": 305
    },
    {
      "tradeDate": "2026-07-01",
      "open": 43.95,
      "high": 43.95,
      "low": 43.55,
      "close": 43.75,
      "change": 0.15,
      "volume": 129086,
      "tradingAmount": 5638034,
      "transactionCount": 197
    },
    {
      "tradeDate": "2026-07-02",
      "open": 43.75,
      "high": 44.2,
      "low": 43.55,
      "close": 44,
      "change": 0.25,
      "volume": 266681,
      "tradingAmount": 11715020,
      "transactionCount": 328
    },
    {
      "tradeDate": "2026-07-03",
      "open": 41.1,
      "high": 41.65,
      "low": 41,
      "close": 41.65,
      "change": 0,
      "volume": 366064,
      "tradingAmount": 15162868,
      "transactionCount": 652
    },
    {
      "tradeDate": "2026-07-06",
      "open": 41.65,
      "high": 41.75,
      "low": 41.35,
      "close": 41.5,
      "change": -0.15,
      "volume": 206203,
      "tradingAmount": 8568431,
      "transactionCount": 444
    },
    {
      "tradeDate": "2026-07-07",
      "open": 41.5,
      "high": 41.5,
      "low": 41.05,
      "close": 41.25,
      "change": -0.25,
      "volume": 189005,
      "tradingAmount": 7784217,
      "transactionCount": 436
    },
    {
      "tradeDate": "2026-07-08",
      "open": 41.25,
      "high": 41.25,
      "low": 40.9,
      "close": 41.25,
      "change": 0,
      "volume": 106825,
      "tradingAmount": 4384781,
      "transactionCount": 305
    },
    {
      "tradeDate": "2026-07-09",
      "open": 41.1,
      "high": 41.45,
      "low": 41,
      "close": 41.4,
      "change": 0.15,
      "volume": 98111,
      "tradingAmount": 4038566,
      "transactionCount": 205
    },
    {
      "tradeDate": "2026-07-13",
      "open": 41.3,
      "high": 41.35,
      "low": 40.7,
      "close": 40.95,
      "change": -0.45,
      "volume": 133999,
      "tradingAmount": 5476722,
      "transactionCount": 348
    },
    {
      "tradeDate": "2026-07-14",
      "open": 41.3,
      "high": 41.3,
      "low": 40.35,
      "close": 40.65,
      "change": -0.3,
      "volume": 141386,
      "tradingAmount": 5733999,
      "transactionCount": 276
    },
    {
      "tradeDate": "2026-07-15",
      "open": 40.7,
      "high": 41.5,
      "low": 40.65,
      "close": 40.9,
      "change": 0.25,
      "volume": 118344,
      "tradingAmount": 4838484,
      "transactionCount": 172
    },
    {
      "tradeDate": "2026-07-16",
      "open": 41.4,
      "high": 41.4,
      "low": 40.5,
      "close": 41,
      "change": 0.1,
      "volume": 75815,
      "tradingAmount": 3109891,
      "transactionCount": 101
    },
    {
      "tradeDate": "2026-07-17",
      "open": 41,
      "high": 41,
      "low": 40.5,
      "close": 40.5,
      "change": -0.5,
      "volume": 147203,
      "tradingAmount": 6004047,
      "transactionCount": 237
    },
    {
      "tradeDate": "2026-07-20",
      "open": 41,
      "high": 41.25,
      "low": 40.8,
      "close": 41.1,
      "change": 0.6,
      "volume": 129319,
      "tradingAmount": 5301129,
      "transactionCount": 158
    },
    {
      "tradeDate": "2026-07-21",
      "open": 41.1,
      "high": 41.5,
      "low": 41.1,
      "close": 41.25,
      "change": 0.15,
      "volume": 68773,
      "tradingAmount": 2843105,
      "transactionCount": 113
    }
  ]
}
