{
  "symbol": "6191",
  "name": "精成科",
  "tradeDate": "2026-07-17",
  "market": "TWSE",
  "instrumentType": "stock",
  "quote": {
    "open": 92,
    "high": 92,
    "low": 87.8,
    "close": 89.2,
    "change": -4.3,
    "changePercent": -4.6,
    "tradeVolume": 6423729,
    "transactionCount": 6193,
    "tradeValue": 572300645,
    "peRatio": 13.89
  },
  "dailyRangePercent": 4.78,
  "turnoverAverageValue": 92410.89,
  "pricePosition": 33.3,
  "liquidityScore": 82.8,
  "priceStrengthScore": 29.8,
  "valuationRiskScore": 20,
  "snapshotScore": 58.4,
  "status": "中性",
  "risks": [],
  "tags": [
    "中性",
    "下跌"
  ],
  "sources": [
    {
      "type": "official",
      "name": "TWSE",
      "field": "quote"
    },
    {
      "type": "derived",
      "name": "GULI deterministic rules",
      "field": "scores"
    }
  ],
  "warnings": []
}
